[
  {
    "date": "2026-03-31",
    "title": "Alfa Laval to drive water transition dialogue at Global Water Summit 2026 in Madrid",
    "ko_title": "알파라발, 2026 글로벌 물 회의에서 물 전환 논의 주도",
    "brief": "알파라발이 2026 글로벌 물 회의에서 물 재이용과 혁신을 주제로 논의합니다. 물 보안 문제 해결을 위한 협력과 행동이 강조됩니다.",
    "summary": "유럽에서 물 재이용 비율이 7%에 불과하고, 전 세계적으로 절반의 폐수가 처리되지 않는 상황에서 물 보안 문제가 심각해지고 있습니다. 2026년 마드리드에서 열리는 글로벌 물 회의에서 알파라발은 혁신과 협력을 통해 물 전환을 가속화하고 산업의 운영 회복력을 강화하는 방안을 논의할 예정입니다. 알파라발은 규제 기준을 충족하는 것을 넘어, 개별 폐수의 원천에서 적극적으로 처리하여 물 재이용과 자원 회수를 촉진하는 접근 방식을 지지하고 있습니다. 이러한 논의는 수처리 산업의 지속 가능성과 효율성을 높이는 데 중요한 역할을 할 것입니다.",
    "why_important": "물 재이용은 산업과 지방 정부의 물 보안 전략에서 점점 더 중심적인 역할을 하고 있습니다. 이는 시장의 지속 가능성과 규제 준수 측면에서 매우 중요합니다.",
    "category": "재이용수",
    "countries": [
      "스페인"
    ],
    "companies": [
      "알파라발"
    ],
    "technologies": [
      "물 재이용",
      "폐수",
      "막"
    ],
    "policy_alert": "",
    "source": "WaterNewsWire Full Text",
    "link": "https://waternewswire.com/news/2026/alfa-laval-global-water-summit-2026-madrid-water-reuse-innovation-strategy",
    "score": 38,
    "keywords": [
      "membrane",
      "wastewater",
      "water reuse",
      "effluent",
      "water treatment"
    ]
  },
  {
    "date": "2026-05-21",
    "title": "Climate Solutions Prize Unveils 2026 Top 10 Finalists Ahead of Largest Festival Yet in Montréal, June 8–9",
    "ko_title": "2026 기후 솔루션 상, 몬트리올에서 결선 진출자 발표",
    "brief": "2026 기후 솔루션 상의 결선 진출자 10팀이 발표되었습니다. 이번 축제는 기후 기술 혁신을 위한 중요한 플랫폼이 될 것입니다.",
    "summary": "2026 기후 솔루션 상 축제가 몬트리올에서 개최됩니다. 이번 축제에서는 기후 기술 혁신을 위한 10개의 결선 진출자가 발표되며, 이들은 투자자와 산업 리더들 앞에서 발표를 진행합니다. 축제는 6월 8일부터 9일까지 진행되며, 2,000명이 참석할 것으로 예상됩니다. 수처리 산업과 관련하여, 기후 기술의 발전은 물 관리와 오염 문제 해결에 중요한 역할을 할 수 있습니다.",
    "why_important": "기후 기술의 발전은 수처리 산업의 혁신을 촉진할 수 있습니다. 이는 시장의 지속 가능성과 규제 준수 측면에서 중요한 의미를 갖습니다.",
    "category": "수처리 산업동향",
    "countries": [
      "캐나다"
    ],
    "companies": [],
    "technologies": [
      "water treatment",
      "pfas",
      "award"
    ],
    "policy_alert": "",
    "source": "WaterNewsWire Full Text",
    "link": "https://waternewswire.com/news/2026/climate-solutions-prize-2026-festival-finalists-montreal",
    "score": 35,
    "keywords": [
      "water treatment",
      "pfas",
      "award",
      "expansion",
      "funding",
      "investment"
    ]
  },
  {
    "date": "2026-03-10",
    "title": "Decent Holding Inc. (Nasdaq: DXST) Announces Strategic Cooperation to Expand AI-Enabled Community Healthcare Network in China",
    "ko_title": "Decent Holding, 중국에서 AI 기반 건강 네트워크 확장",
    "brief": "Decent Holding의 자회사 Suncare가 중국에서 지역 노인 돌봄 운영자와 전략적 협력 계약을 체결했습니다. 이 협약은 AI 기반 디지털 건강 솔루션을 통합하여 커뮤니티 서비스 위치를 70곳으로 확장할 계획입니다.",
    "summary": "Decent Holding Inc.는 최근 노인 건강 및 웰빙 부문에 진출한 폐수 처리 서비스 제공업체입니다. 자회사 Suncare는 중국의 지역 노인 돌봄 운영자와 전략적 협력 계약을 체결하여 AI 기반 디지털 건강 플랫폼을 통합할 예정입니다. 이 협약은 동부 및 북부 중국의 여러 지방에서 약 70개의 커뮤니티 서비스 위치를 확장하는 것을 목표로 합니다. 각 위치는 약 30,000에서 100,000명의 주민 커뮤니티에 예방 건강 상담 및 라이프스타일 관리 서비스를 제공합니다. 이는 수처리 산업과 건강 관리의 융합을 보여주는 사례로, 향후 시장 확장에 기여할 것으로 예상됩니다.",
    "why_important": "이 협약은 수처리 산업과 건강 관리의 융합을 통해 새로운 시장 기회를 창출할 수 있습니다. 또한, AI 기술을 활용한 서비스 확장은 향후 기술 발전과 규제 변화에 대응하는 중요한 사례가 될 것입니다.",
    "category": "기업동향",
    "countries": [
      "중국"
    ],
    "companies": [
      "Decent Holding Inc.",
      "Suncare (Shanghai) Health Technology Co., Ltd."
    ],
    "technologies": [
      "AI",
      "Digital Health",
      "Wastewater Treatment"
    ],
    "policy_alert": "",
    "source": "WaterNewsWire Full Text",
    "link": "https://waternewswire.com/news/2026/healthcare-china-decent-holding-dxst-community-health-network-expansion",
    "score": 23,
    "keywords": [
      "wastewater",
      "industrial wastewater",
      "water treatment"
    ]
  },
  {
    "date": "2026-02-20",
    "title": "Canadian Water and Wastewater Association and Water Canada Announce Strategic Partnership to Elevate the Water Canada Awards",
    "ko_title": "캐나다 수처리 협회, 워터 캐나다와 파트너십 체결",
    "brief": "캐나다 수처리 협회(CWWA)와 워터 캐나다가 전략적 파트너십을 체결했습니다. 이로 인해 2026년 워터 캐나다 어워드가 새로운 카테고리를 추가하여 지방 정부의 성과를 기립니다.",
    "summary": "캐나다 수처리 협회(CWWA)와 워터 캐나다가 전략적 파트너십을 체결하여 캐나다 수처리 분야의 우수성을 인정하는 방안을 통합했습니다. 이번 협력으로 2026년 워터 캐나다 어워드에 두 개의 새로운 카테고리가 추가되어 지방 정부의 기여를 강조합니다. 이는 지역 정부가 캐나다의 중요한 자원을 관리하는 데 있어 중요한 역할을 하고 있음을 보여줍니다. 이러한 변화는 수처리 산업의 발전과 협력을 촉진할 것으로 기대됩니다.",
    "why_important": "이번 파트너십은 캐나다 수처리 산업의 인식을 높이고 지방 정부의 기여를 강조하는 데 중요한 의미를 갖습니다. 이는 향후 수처리 관련 프로젝트와 정책에 긍정적인 영향을 미칠 것으로 보입니다.",
    "category": "프로젝트/수주",
    "countries": [
      "캐나다"
    ],
    "companies": [],
    "technologies": [],
    "policy_alert": "",
    "source": "WaterNewsWire Full Text",
    "link": "https://waternewswire.com/news/2026/water-canada-awards-2026-partnership",
    "score": 23,
    "keywords": [
      "wastewater",
      "award",
      "upgrade",
      "pilot"
    ]
  },
  {
    "date": "2025-02-27",
    "title": "02271pfas-problem",
    "ko_title": "PFAS 문제, 수처리 산업의 새로운 도전",
    "brief": "PFAS에 대한 공공 인식이 높아지고 있습니다. 이는 수처리 산업에 중요한 영향을 미칠 수 있습니다.",
    "summary": "PFAS(퍼플루오로알킬물질)에 대한 관심이 증가하고 있으며, 이는 건강 문제로 부각되고 있습니다. 최근 IDTechEx의 보고서는 PFAS와 관련된 규제가 산업에 미치는 영향을 분석하고 있습니다. PFAS는 다양한 산업에서 사용되며, 수돗물에서의 PFAS 처리 문제는 수처리 산업에 큰 도전 과제가 되고 있습니다. 이러한 문제는 새로운 기술 개발과 규제 대응을 촉진할 것으로 예상됩니다.",
    "why_important": "PFAS 문제는 수처리 산업의 규제 환경을 변화시킬 수 있습니다. 이는 기업들이 새로운 기술을 개발하고, 시장에서의 경쟁력을 유지하기 위해 대응해야 함을 의미합니다.",
    "category": "PFAS/오염물",
    "countries": [],
    "companies": [],
    "technologies": [
      "PFAS",
      "membrane",
      "drinking water"
    ],
    "policy_alert": "",
    "source": "WaterNewsWire Full Text",
    "link": "https://waternewswire.com/news/2025/02271pfas-problem",
    "score": 23,
    "keywords": [
      "membrane",
      "drinking water",
      "pfas"
    ]
  },
  {
    "date": "2025-02-25",
    "title": "Green hydrogen economy: Evonik is building a plant for anion exchange membranes",
    "ko_title": "에보닉, 음이온 교환막 생산 파일럿 공장 건설",
    "brief": "에보닉이 독일 말르에 음이온 교환막 생산을 위한 파일럿 공장을 건설합니다. 이 공장은 2025년 말 가동될 예정입니다.",
    "summary": "에보닉은 독일 말르에 혁신적인 음이온 교환막(AEM) 생산을 위한 파일럿 공장을 건설하고 있습니다. 이 막은 DURAION®이라는 이름으로 판매되며, 녹색 수소 생산에 필수적인 요소입니다. 에보닉은 이 공장에 수십억 유로를 투자하고 있으며, 2025년 말 가동을 목표로 하고 있습니다. 이 투자는 에보닉의 사업 목표와 연계되어 있으며, 녹색 수소 경제의 발전에 기여할 것으로 기대됩니다. 수처리 산업에서 이러한 기술은 지속 가능한 에너지 생산에 중요한 역할을 할 것입니다.",
    "why_important": "녹색 수소 경제의 발전은 수처리 산업에 새로운 기회를 제공합니다. 이 기술은 수소 생산의 비용 경쟁력을 높여 시장의 변화를 이끌 것으로 추측입니다.",
    "category": "분리막/MBR",
    "countries": [
      "독일"
    ],
    "companies": [
      "에보닉"
    ],
    "technologies": [
      "음이온 교환막",
      "녹색 수소"
    ],
    "policy_alert": "",
    "source": "WaterNewsWire Full Text",
    "link": "https://waternewswire.com/news/2025/02251green-hydrogen-economy",
    "score": 22,
    "keywords": [
      "membrane",
      "expansion",
      "pilot",
      "investment"
    ]
  },
  {
    "date": "2024-12-06",
    "title": "Breaking Cleantech Automotive Stock News: Worksport (NASDAQ: WKSP) Sees 51% B2C and 60% B2B Sales Growth in November, Boosting Margins, and Accelerating Brand Expansion",
    "ko_title": "Worksport, 11월 B2C 51% 및 B2B 60% 성장",
    "brief": "Worksport가 2024년 11월 B2C 및 B2B 부문에서 각각 51%와 60%의 매출 성장을 기록했습니다. 이는 브랜드 확장과 마진 개선에 기여하고 있습니다.",
    "summary": "Worksport Ltd.는 2024년 11월 B2C와 B2B 부문에서 각각 51%와 60%의 매출 성장을 발표했습니다. 이 회사는 고수익성 브랜드 제품 판매에 집중하며, 낮은 마진의 프라이빗 레이블 프로그램을 중단했습니다. 이러한 변화는 수익성 개선을 목표로 하고 있으며, 특히 연말 시즌 동안 수요가 급증했습니다. 수처리 산업과의 직접적인 연관성은 없지만, 청정 기술 분야의 성장은 지속 가능한 솔루션에 대한 관심을 반영합니다.",
    "why_important": "이러한 성장은 청정 기술 시장의 성장 가능성을 보여줍니다. 수처리 산업에서도 지속 가능한 기술 개발이 중요해지고 있으며, 이는 시장의 변화에 영향을 미칠 수 있습니다.",
    "category": "기업동향",
    "countries": [
      "미국"
    ],
    "companies": [
      "Worksport Ltd."
    ],
    "technologies": [
      "청정 기술"
    ],
    "policy_alert": "",
    "source": "WaterNewsWire Full Text",
    "link": "https://waternewswire.com/news/2024/12061wksp-b2b-sales-growth-in-november",
    "score": 19,
    "keywords": [
      "tender",
      "award",
      "expansion",
      "investment"
    ]
  },
  {
    "date": "2026-04-09",
    "title": "Countries pledge $3.9 billion to Global Environment Facility towards ambitious ninth replenishment",
    "ko_title": "국가들, 글로벌 환경 기금에 39억 달러 약속",
    "brief": "개발도상국의 2030 환경 목표를 지원하기 위해 39억 달러의 자금이 약속되었습니다. 이는 다자간 협력을 통한 국제 환경 목표 달성을 위한 강력한 의지를 보여줍니다.",
    "summary": "국제 사회는 글로벌 환경 기금(GEF)의 아홉 번째 자금 보충을 위해 39억 달러를 약속했습니다. 이 자금은 개발도상국이 환경 목표를 달성하고 자연 친화적인 발전을 촉진하는 데 사용될 것입니다. 이러한 투자로 인해 개발도상국은 긴급한 환경 문제를 해결하고, 글로벌 환경 혜택을 창출할 수 있을 것으로 기대됩니다. 수처리 산업은 이러한 환경 목표 달성에 중요한 역할을 할 수 있습니다.",
    "why_important": "이 자금 약속은 개발도상국의 환경 관리 및 수처리 기술 발전에 기여할 수 있습니다. 이는 수처리 산업의 성장과 지속 가능성에 긍정적인 영향을 미칠 것으로 추측됩니다.",
    "category": "규제/정책",
    "countries": [],
    "companies": [],
    "technologies": [],
    "policy_alert": "글로벌 환경 기금의 자금 지원은 환경 규제 강화와 관련이 있습니다.",
    "source": "WaterNewsWire Full Text",
    "link": "https://waternewswire.com/news/2026/global-environment-facility-3-9-billion-pledge-gef9-funding-2030-environment-goals",
    "score": 13,
    "keywords": [
      "demonstration",
      "funding",
      "investment"
    ]
  },
  {
    "date": "2025-01-16",
    "title": "Water Sector Organizations Partner on Innovative Generative AI Research Project",
    "ko_title": "수처리 분야, 생성형 AI 연구 프로젝트 시작",
    "brief": "미국 수처리 관련 기관들이 생성형 AI 연구 프로젝트를 시작했습니다. 이 프로젝트는 수처리 산업의 혁신적인 기술 적용을 위한 기초를 마련할 것입니다.",
    "summary": "미국의 수처리 관련 기관들이 생성형 AI의 역할을 연구하기 위한 프로젝트를 시작했습니다. 이 연구는 수처리 유틸리티에 대한 생성형 AI의 기초 이해를 확립하고, 최선의 사례 및 응용 프로그램을 공유하는 데 중점을 두고 있습니다. 또한, 향후 수처리 분야에서의 생성형 AI 응용을 위한 연구 로드맵을 수립할 예정입니다. AWWA의 CEO는 생성형 AI가 수처리 커뮤니티를 혁신적으로 변화시킬 것이라고 강조했습니다.",
    "why_important": "이 연구는 수처리 산업의 기술 혁신을 촉진할 수 있는 중요한 기초 자료를 제공합니다. 생성형 AI의 도입은 운영 효율성을 높이고, 새로운 비즈니스 모델을 창출할 가능성이 있습니다.",
    "category": "수처리 산업동향",
    "countries": [
      "미국"
    ],
    "companies": [
      "American Water Works Association",
      "Water Environment Federation",
      "Water Research Foundation",
      "Karmous Edwards Consulting"
    ],
    "technologies": [
      "Generative AI"
    ],
    "policy_alert": "",
    "source": "WaterNewsWire Full Text",
    "link": "https://waternewswire.com/news/2025/01161innovative-generative-ai-research-project",
    "score": 13,
    "keywords": [
      "wastewater",
      "drinking water"
    ]
  },
  {
    "date": "2024-12-30",
    "title": "The Water Investing Story Gets Bigger with Solutions to PFAS and more...",
    "ko_title": "PFAS 해결책으로 물 투자 이야기 확대",
    "brief": "PFAS 문제 해결을 위한 투자 기회가 증가하고 있습니다. 수처리 산업에서의 혁신이 주목받고 있습니다.",
    "summary": "최근 PFAS(영구화학물질) 문제 해결을 위한 다양한 투자 기회가 부각되고 있습니다. 이러한 문제는 수처리 산업에 큰 영향을 미치며, 새로운 기술과 솔루션이 필요합니다. PFAS는 환경과 인체에 미치는 영향이 크기 때문에, 이를 해결하기 위한 연구와 개발이 활발히 진행되고 있습니다. 수처리 기업들은 이러한 기회를 통해 시장에서 경쟁력을 강화할 수 있습니다.",
    "why_important": "PFAS 문제 해결은 수처리 산업의 혁신을 촉진할 수 있습니다. 이는 규제 강화와 함께 시장의 성장 가능성을 높이는 중요한 요소입니다.",
    "category": "PFAS/오염물",
    "countries": [],
    "companies": [],
    "technologies": [
      "PFAS"
    ],
    "policy_alert": "",
    "source": "WaterNewsWire",
    "link": "https://waternewswire.com/news/2024/12302water-investing-story",
    "score": 10,
    "keywords": [
      "pfas"
    ]
  },
  {
    "date": "2024-11-25",
    "title": "Breaking Renewable Energy and Defense Stock News: KULR (NYSE: KULR) Awarded U.S. Navy Contract to Develop High-Temperature Internal Short Circuit Cells for Enhanced Battery Safety in Critical Applications",
    "ko_title": "KULR, 미 해군 계약 수주로 배터리 안전성 강화",
    "brief": "KULR이 미 해군과 계약을 체결하여 고온 내부 단락 셀을 개발합니다. 이는 중요한 응용 분야에서 배터리 안전성을 향상시키기 위한 것입니다.",
    "summary": "KULR은 미 해군과의 계약을 통해 고온 내부 단락 셀 개발에 착수합니다. 이 기술은 배터리의 안전성을 높이고, 특히 군사 및 방위 분야에서의 응용 가능성을 확대할 것으로 기대됩니다. 수처리 산업과의 직접적인 연관성은 없지만, 배터리 기술의 발전은 에너지 효율성을 높이는 데 기여할 수 있습니다. 이는 지속 가능한 에너지 솔루션을 찾는 수처리 산업에 간접적인 영향을 미칠 수 있습니다.",
    "why_important": "이 계약은 방위 산업의 기술 혁신을 촉진할 수 있습니다. 또한, 에너지 효율성이 향상되면 수처리 시설의 운영 비용 절감에도 기여할 수 있습니다.",
    "category": "기업동향",
    "countries": [
      "미국"
    ],
    "companies": [
      "KULR"
    ],
    "technologies": [
      "배터리 안전성",
      "고온 내부 단락 셀"
    ],
    "policy_alert": "",
    "source": "WaterNewsWire",
    "link": "https://waternewswire.com/news/2024/11251kulr-us-navy-contract-high-temperature-internal-short-circuit-cells",
    "score": 10,
    "keywords": [
      "contract",
      "award"
    ]
  },
  {
    "date": "2024-12-09",
    "title": "New type of battery could outlast EVs and still be used for grid energy storage",
    "ko_title": "새로운 배터리, EV보다 긴 수명 기대",
    "brief": "리튬 이온 배터리의 수명을 늘리려는 노력이 진행 중이다. 새로운 배터리는 전기차 사용 후에도 에너지 저장에 활용될 수 있다.",
    "summary": "리튬 이온 배터리의 수명을 늘리기 위한 연구가 진행되고 있으며, 이는 전기차(EV)에서의 사용 후에도 에너지 저장에 활용될 수 있는 가능성을 제시한다. 캐나다 다르하우지 대학의 연구진은 새로운 배터리가 수십 년 동안 사용될 수 있도록 설계되었다고 발표했다. 이러한 기술은 재생 가능 에너지를 저장하여 전력망에 공급하는 '세컨드 라이프' 응용 프로그램에 적합하다. 수처리 산업에서도 지속 가능한 에너지 솔루션이 필요하므로, 이러한 배터리 기술의 발전은 관련성이 높다.",
    "why_important": "이 기술은 에너지 저장 솔루션의 지속 가능성을 높여 시장의 요구에 부응할 수 있다. 또한, 재생 가능 에너지의 활용을 극대화하여 수처리 산업의 에너지 효율성을 개선할 가능성이 있다.",
    "category": "수처리 산업동향",
    "countries": [
      "캐나다",
      "미국"
    ],
    "companies": [],
    "technologies": [
      "리튬 이온 배터리",
      "에너지 저장"
    ],
    "policy_alert": "",
    "source": "WaterNewsWire Full Text",
    "link": "https://waternewswire.com/news/2024/12091battery-grid-energy-storage",
    "score": 10,
    "keywords": [
      "contract",
      "expansion"
    ]
  },
  {
    "date": "2026-02-18",
    "title": "BC Budget Misses Opportunity to Generate New Revenue, Strengthen Watershed Security, Jobs, and Economic Resilience",
    "ko_title": "BC 예산, 수자원 보안 강화 기회 놓쳐",
    "brief": "2026년 BC 예산은 수자원 보안 강화를 위한 기회를 놓쳤습니다. 기후 변화와 불확실성이 커지는 가운데, 산업용수 요금 현대화에 대한 약속이 없습니다.",
    "summary": "2026년 브리티시컬럼비아(B.C.) 예산은 주의 경제와 공공 안전을 뒷받침하는 수자원 보안 강화를 위한 중요한 기회를 놓쳤습니다. 기후 변화로 인한 극단적인 상황이 증가하고 있는 가운데, 예산은 수자원 보안에 대한 새로운 투자를 포함하지 않았습니다. 또한, 산업용수 요금의 현대화에 대한 약속도 없어 물의 경제적 가치가 저평가되고 있다는 우려가 제기되고 있습니다. 이러한 상황은 지역 사회와 기업에 심각한 영향을 미칠 수 있습니다.",
    "why_important": "이 예산은 수자원 관리와 관련된 규제 및 정책의 중요성을 강조합니다. 안정적인 수자원 확보 없이는 경제와 일자리 보호가 어려울 것으로 보입니다.",
    "category": "규제/정책",
    "countries": [
      "캐나다"
    ],
    "companies": [],
    "technologies": [
      "funding",
      "investment"
    ],
    "policy_alert": "수자원 보안 강화를 위한 새로운 투자와 산업용수 요금 현대화가 필요합니다.",
    "source": "WaterNewsWire Full Text",
    "link": "https://waternewswire.com/news/2026/budget-2026-watershed-security-industrial-water-rates",
    "score": 8,
    "keywords": [
      "funding",
      "investment"
    ]
  },
  {
    "date": "2026-06-01",
    "title": "Malaysia to surpass 2040 renewable energy target by 2031",
    "ko_title": "말레이시아, 2031년까지 재생에너지 목표 초과 달성",
    "brief": "말레이시아가 2031년까지 2040년 재생에너지 목표를 초과 달성할 것으로 보입니다. 대규모 태양광 입찰과 강력한 정책이 주요 요인입니다.",
    "summary": "말레이시아는 2040년까지 18.43GW의 재생에너지 용량 목표를 설정했으나, 2031년까지 이를 초과 달성할 것으로 예상됩니다. 이는 대규모 태양광 입찰과 강력한 정책 프레임워크, 접근 가능한 금융 지원, 그리고 그리드 통합 및 저장 용량의 개선 덕분입니다. GlobalData의 보고서에 따르면, 말레이시아의 재생에너지 용량은 2025년 약 6.9GW에서 2035년에는 약 31.5GW로 증가할 것으로 보입니다. 이러한 발전은 수처리 산업에도 긍정적인 영향을 미칠 수 있습니다.",
    "why_important": "재생에너지의 증가는 수처리 산업의 지속 가능성을 높이는 데 기여할 수 있습니다. 이는 시장의 변화와 기술 발전에 중요한 영향을 미칠 것으로 보입니다.",
    "category": "수처리 산업동향",
    "countries": [
      "말레이시아"
    ],
    "companies": [],
    "technologies": [
      "재생에너지",
      "태양광"
    ],
    "policy_alert": "",
    "source": "WaterNewsWire Full Text",
    "link": "https://waternewswire.com/news/2026/malaysia-renewable-energy-2040-target-2031-globaldata",
    "score": 19,
    "keywords": [
      "tender",
      "contract",
      "expansion",
      "investment"
    ]
  },
  {
    "date": "2024-11-25",
    "title": "Membrane Bioreactor Market Global Forecast to 2029 - Increasing Demand for Effective Wastewater Treatment, Rising Stringent Environmental Regulations Standards & Growing ...",
    "ko_title": "막생물반응기 시장 2029년까지 성장 전망",
    "brief": "막생물반응기(MBR) 시장이 2029년까지 성장할 것으로 예상됩니다. 폐수 처리의 효과적인 수요 증가와 환경 규제 강화가 주요 요인입니다.",
    "summary": "막생물반응기(MBR) 시장은 2029년까지 지속적인 성장이 예상됩니다. 이는 효과적인 폐수 처리에 대한 수요 증가와 함께 환경 규제가 강화되고 있기 때문입니다. MBR 기술은 다양한 막 유형과 시스템 구성으로 제공되며, 이는 수처리 산업에서 중요한 역할을 하고 있습니다. 특히, 환경 보호와 지속 가능한 개발을 위한 기술적 진보가 필요합니다.",
    "why_important": "MBR 기술은 폐수 처리의 효율성을 높이는 데 중요한 역할을 하며, 이는 시장에서의 경쟁력을 강화합니다. 또한, 환경 규제의 강화는 MBR 기술의 채택을 촉진할 것으로 예상됩니다.",
    "category": "막여과/MBR",
    "countries": [],
    "companies": [],
    "technologies": [
      "MBR",
      "막생물반응기",
      "폐수 처리"
    ],
    "policy_alert": "",
    "source": "Bing News Global MBR",
    "link": "http://www.bing.com/news/apiclick.aspx?ref=FexRss&aid=&tid=6a1e8c5f50d24c6cbb6959fcc3b8ab6d&url=https%3a%2f%2ffinance.yahoo.com%2fnews%2fmembrane-bioreactor-market-global-forecast-114100669.html&c=16621848752719979235&mkt=en-us",
    "score": 51,
    "keywords": [
      "mbr",
      "membrane bioreactor",
      "membrane",
      "hollow fiber",
      "wastewater",
      "water treatment"
    ],
    "domestic": false,
    "region": "global",
    "source_type": "search_rss"
  },
  {
    "date": "2021-10-19",
    "title": "Watercore Membrane Bioreactor (MBR) : the highest effluent quality in wastewater treatment",
    "ko_title": "Watercore MBR: 폐수 처리의 최고 품질",
    "brief": "Watercore MBR은 환경 민감 지역에 방류할 수 있는 고품질의 폐수를 생산합니다. 이 기술은 재활용에도 적합하여 수처리 산업에 중요한 역할을 합니다.",
    "summary": "Watercore MBR(막 생물 반응기)은 폐수 처리에서 가장 높은 품질의 방류수를 생산하는 기술입니다. 이 시스템은 환경적으로 민감한 지역에 방류할 수 있는 고품질의 폐수를 생성하며, 재활용에도 적합합니다. MBR 기술은 수처리 산업에서 중요한 혁신으로 자리잡고 있으며, 지속 가능한 수자원 관리에 기여하고 있습니다. 이러한 기술 발전은 수처리의 효율성을 높이고, 환경 보호에 기여할 수 있습니다.",
    "why_important": "MBR 기술은 수처리 산업의 효율성을 높이고, 환경 보호에 기여할 수 있는 중요한 혁신입니다. 시장에서의 경쟁력을 강화하고, 규제 준수에 도움이 될 것으로 예상됩니다.",
    "category": "분리막/MBR",
    "countries": [],
    "companies": [],
    "technologies": [
      "MBR",
      "막 생물 반응기",
      "폐수 처리"
    ],
    "policy_alert": "",
    "source": "Bing News Global MBR",
    "link": "http://www.bing.com/news/apiclick.aspx?ref=FexRss&aid=&tid=6a1e8c5f50d24c6cbb6959fcc3b8ab6d&url=https%3a%2f%2fmenafn.com%2f1102994693%2fWatercore-Membrane-Bioreactor-MBR-the-highest-effluent-quality-in-wastewater-treatment&c=6585496301972639428&mkt=en-us",
    "score": 49,
    "keywords": [
      "mbr",
      "membrane bioreactor",
      "membrane",
      "wastewater",
      "effluent",
      "water treatment"
    ],
    "domestic": false,
    "region": "global",
    "source_type": "search_rss"
  },
  {
    "date": "2023-12-12",
    "title": "Indirect Evidence that Colloidal Deposition Inside a Hollow Fiber Ultrafiltration Membrane Exacerbated Fouling during Municipal Wastewater Reclamation - ACS Publications",
    "ko_title": "막여과막 내 콜로이드 침착의 영향 분석",
    "brief": "막여과막 내부의 콜로이드 침착이 도시 폐수 재활용 과정에서 오염을 악화시켰다는 간접 증거가 제시되었습니다. 이 연구는 수처리 산업에 중요한 시사점을 제공합니다.",
    "summary": "최근 연구에서 막여과막 내부의 콜로이드 침착이 도시 폐수 재활용 과정에서 오염을 악화시켰다는 간접 증거가 발견되었습니다. 이 연구는 막여과 기술의 효율성에 대한 새로운 통찰을 제공하며, 수처리 공정에서의 오염 문제를 해결하기 위한 필요성을 강조합니다. 특히, 도시 폐수 재활용의 중요성이 커지는 가운데, 이러한 연구 결과는 수처리 산업의 기술 발전에 기여할 수 있습니다. 연구 결과는 향후 수처리 시스템의 설계 및 운영에 중요한 영향을 미칠 것으로 예상됩니다.",
    "why_important": "이 연구는 막여과 기술의 성능 개선을 위한 중요한 정보를 제공합니다. 수처리 산업에서 오염 문제 해결은 시장 경쟁력과 직결되므로 매우 중요합니다.",
    "category": "분리막/막여과",
    "countries": [],
    "companies": [],
    "technologies": [
      "막여과",
      "콜로이드",
      "폐수 재활용"
    ],
    "policy_alert": "",
    "source": "Google News Global Membrane MBR",
    "link": "https://news.google.com/rss/articles/CBMiYEFVX3lxTFBSUm4zQ0k4N05hNDY0MlR6M2xfQkxyQzQtbmloYnMwUDAyaWZrYUdtd1NtbmhxamJMYkZVLW5WSUxaSmdCV29FcmdqMlpXVWpsdDZpOTFuNjR0Y3V0UnJkVA?oc=5",
    "score": 39,
    "keywords": [
      "membrane",
      "hollow fiber",
      "ultrafiltration",
      "wastewater",
      "cip"
    ],
    "domestic": false,
    "region": "global",
    "source_type": "search_rss"
  },
  {
    "date": "2014-10-24",
    "title": "[대한민국 물산업전 영상] 에코니티, 수처리용 가압형 중공사막 모듈 'ECONITY PF Series'선봬 - 에이빙",
    "ko_title": "에코니티, 수처리용 중공사막 모듈 공개",
    "brief": "에코니티가 대한민국 물산업전에서 가압형 중공사막 모듈 'ECONITY PF Series'를 선보였습니다. 이 기술은 수처리 산업에서 중요한 혁신으로 평가받고 있습니다.",
    "summary": "대한민국 물산업전에서 에코니티는 새로운 가압형 중공사막 모듈인 'ECONITY PF Series'를 공개했습니다. 이 모듈은 수처리 효율성을 높이고, 다양한 수질 조건에서도 안정적인 성능을 발휘할 수 있도록 설계되었습니다. 중공사막 기술은 물 처리 과정에서 중요한 역할을 하며, 특히 산업폐수 처리 및 재이용수 분야에서의 활용 가능성이 큽니다. 에코니티의 신제품은 수처리 산업의 기술 발전에 기여할 것으로 기대됩니다.",
    "why_important": "이 기술은 수처리 효율성을 높이는 데 기여할 수 있어 시장에서의 경쟁력을 강화할 수 있습니다. 또한, 환경 규제가 강화되는 가운데, 혁신적인 수처리 솔루션은 기업의 지속 가능성을 높이는 데 중요한 역할을 할 것입니다.",
    "category": "분리막/MBR",
    "countries": [
      "대한민국"
    ],
    "companies": [
      "에코니티"
    ],
    "technologies": [
      "중공사막"
    ],
    "policy_alert": "",
    "source": "Google News Korea 막여과 MBR",
    "link": "https://news.google.com/rss/articles/CBMiZ0FVX3lxTE9vOFVPXzZYaWJWUF9QNk80RlhFRm9fbWxfV1hGeVgzS2h2aVpUdGl2U3RxQ3MteVVoZFZDNTh1ZlpjQTZESGNhSkc1WEhnYkpkTHRwU0x1Zm8yQzBILVM3TnMwOHphLXfSAWtBVV95cUxQaXEtTGRnVU1CRTlnRU1fNlB2c2xRTjkzTEdGZGh3WEVWaU0yR0N4ZW9kbi0tLUZPd3RhSW9aYlhaM3BBd09GOGtiTW5pRGNhd1V3V2VFX2s0TnlVdmw5LV9TNzUzYk1uNlVrNA?oc=5",
    "score": 36,
    "keywords": [
      "수처리",
      "물산업",
      "중공사막",
      "중공사"
    ],
    "domestic": true,
    "region": "domestic",
    "source_type": "search_rss"
  },
  {
    "date": "2026-02-18",
    "title": "MemCor™ MBR systems selected for three major wastewater treatment plant expansions in England",
    "ko_title": "영국, MemCor™ MBR 시스템으로 하수처리장 확장",
    "brief": "영국에서 MemCor™ MBR 시스템이 세 개의 주요 하수처리장 확장에 선정되었습니다. 이는 수처리 기술의 발전과 투자 확대를 의미합니다.",
    "summary": "영국의 세 개 하수처리장이 MemCor™ MBR 시스템을 도입하여 확장됩니다. 이 시스템은 효율적인 수처리를 통해 환경 보호와 자원 재활용을 촉진할 것으로 기대됩니다. MBR 기술은 고도화된 수처리 솔루션으로, 특히 도시화가 진행되는 지역에서 수요가 증가하고 있습니다. 이러한 확장은 수처리 산업의 기술 발전과 함께 지속 가능한 수자원 관리의 중요성을 강조합니다.",
    "why_important": "이 확장은 MBR 기술의 시장 수요 증가를 나타내며, 향후 수처리 프로젝트에 긍정적인 영향을 미칠 것입니다. 또한, 환경 규제 강화에 따라 효율적인 수처리 기술의 필요성이 더욱 커지고 있습니다.",
    "category": "분리막/MBR",
    "countries": [
      "영국"
    ],
    "companies": [],
    "technologies": [
      "MBR",
      "하수처리",
      "수처리"
    ],
    "policy_alert": "",
    "source": "Bing News Global MBR",
    "link": "http://www.bing.com/news/apiclick.aspx?ref=FexRss&aid=&tid=6a1e8c5f50d24c6cbb6959fcc3b8ab6d&url=https%3a%2f%2ffinance.yahoo.com%2fnews%2fmemcor-mbr-systems-selected-three-140000877.html&c=15153598790819934667&mkt=en-us",
    "score": 34,
    "keywords": [
      "mbr",
      "wastewater",
      "water treatment",
      "expansion",
      "investment"
    ],
    "domestic": false,
    "region": "global",
    "source_type": "search_rss"
  },
  {
    "date": "2023-09-20",
    "title": "Effect of organic loading rates on the performance of membrane bioreactor for wastewater treatment behaviours, fouling, and economic cost - Nature",
    "ko_title": "막생물반응기의 유기 하중률이 미치는 영향",
    "brief": "막생물반응기의 유기 하중률이 수처리 성능에 미치는 영향을 분석한 연구입니다. 오염물질의 오염과 경제적 비용에 대한 결과도 포함되어 있습니다.",
    "summary": "이 연구는 막생물반응기(MBR)의 유기 하중률이 수처리 성능, 오염물질 축적, 경제적 비용에 미치는 영향을 분석합니다. 유기 하중률이 높아질수록 MBR의 성능이 저하되고 오염물질 축적이 증가하는 경향이 관찰되었습니다. 이러한 결과는 수처리 산업에서 MBR의 운영 최적화와 비용 절감에 중요한 시사점을 제공합니다. 연구 결과는 MBR 기술의 효율성을 높이기 위한 전략 수립에 기여할 수 있습니다.",
    "why_important": "MBR 기술의 성능 최적화는 수처리 산업의 효율성을 높이고 운영 비용을 절감하는 데 중요합니다. 이는 시장 경쟁력 강화와 지속 가능한 수자원 관리에 기여할 수 있습니다.",
    "category": "막여과/MBR",
    "countries": [],
    "companies": [],
    "technologies": [
      "막생물반응기",
      "막",
      "폐수",
      "수처리"
    ],
    "policy_alert": "",
    "source": "Google News Global Membrane MBR",
    "link": "https://news.google.com/rss/articles/CBMiX0FVX3lxTE1BdEhvMnNMSWE3WTRNRGVYc0p5QVBUOWJrM0VDaWdpV3g0Wmc1by1tQ3Q0OW5ITjEtRUVReGNjdkVUVHBlUURqQVNjdDYyTXU5N1QzNlNVVWxFalVaUGtn?oc=5",
    "score": 33,
    "keywords": [
      "membrane bioreactor",
      "membrane",
      "wastewater",
      "water treatment"
    ],
    "domestic": false,
    "region": "global",
    "source_type": "search_rss"
  },
  {
    "date": "2015-03-01",
    "title": "Water and Wastewater Treatment Technology Update",
    "ko_title": "수처리 기술 업데이트: 발전소 수질 관리",
    "brief": "발전소의 수처리 및 폐수 관리가 복잡해지고 있습니다. 혁신적인 처리 기술이 이를 해결하는 데 도움을 주고 있습니다.",
    "summary": "발전소에서의 수처리 및 폐수 관리가 점점 더 복잡해지고 있으며, 이에 따라 혁신적인 처리 기술의 필요성이 증가하고 있습니다. 최근에는 전방 삼투압 및 막 생물 반응기(MBR)와 같은 기술이 주목받고 있습니다. 이러한 기술들은 효율적인 수처리를 가능하게 하여 발전소의 운영 효율성을 높이는 데 기여할 수 있습니다. 수처리 산업은 이러한 기술 발전을 통해 더욱 발전할 것으로 기대됩니다.",
    "why_important": "수처리 기술의 혁신은 발전소의 운영 비용 절감과 환경 규제 준수에 중요한 역할을 합니다. 이는 시장 경쟁력을 높이고 지속 가능한 발전을 촉진하는 데 기여할 것입니다.",
    "category": "수처리 산업동향",
    "countries": [],
    "companies": [],
    "technologies": [
      "막 생물 반응기",
      "막",
      "폐수",
      "수처리"
    ],
    "policy_alert": "",
    "source": "Bing News Global MBR",
    "link": "http://www.bing.com/news/apiclick.aspx?ref=FexRss&aid=&tid=6a1e8c5f50d24c6cbb6959fcc3b8ab6d&url=https%3a%2f%2fwww.powermag.com%2fwater-and-wastewater-treatment-technology-update%2f&c=4762957416080451425&mkt=en-us",
    "score": 33,
    "keywords": [
      "membrane bioreactor",
      "membrane",
      "wastewater",
      "water treatment"
    ],
    "domestic": false,
    "region": "global",
    "source_type": "search_rss"
  },
  {
    "date": "2026-05-26",
    "title": "\"버려지던 하수 방류수가 전기로\", 서산시, 공공하수처리장에 '친환경 소수력 발전' 도입 - v.daum.net",
    "ko_title": "서산시, 하수 방류수로 친환경 전기 생산",
    "brief": "서산시가 공공하수처리장에 친환경 소수력 발전을 도입했습니다. 버려지던 하수 방류수를 활용해 전기를 생산하는 혁신적인 프로젝트입니다.",
    "summary": "서산시는 공공하수처리장에 친환경 소수력 발전 시스템을 도입하여 하수 방류수를 전기로 전환하는 프로젝트를 시작했습니다. 이 시스템은 하수 처리 과정에서 발생하는 방류수를 활용하여 지속 가능한 에너지를 생산하는 데 기여합니다. 이러한 접근은 수처리 산업에서 자원의 재활용과 에너지 효율성을 높이는 데 중요한 역할을 할 것으로 기대됩니다. 서산시는 이 프로젝트를 통해 지역 사회의 에너지 자립도를 높이고, 환경 보호에도 기여할 계획입니다.",
    "why_important": "이 프로젝트는 하수 방류수를 에너지 자원으로 활용함으로써 수처리 산업의 혁신을 보여줍니다. 이는 지속 가능한 발전과 에너지 효율성 향상에 기여할 것으로 예상됩니다.",
    "category": "프로젝트/수주",
    "countries": [
      "대한민국"
    ],
    "companies": [],
    "technologies": [
      "소수력 발전",
      "하수처리"
    ],
    "policy_alert": "",
    "source": "Google News Korea 상하수도",
    "link": "https://news.google.com/rss/articles/CBMiVEFVX3lxTE1pbTA4ZUdvTkhEcVBtVzNwTG9waTFuZnpvY24zTXBSajgtWEZ4UDRuNmJIY0VPNjVNUS1Temw4WUdadTFmd3JsUXpzSEczMlRObkNIaw?oc=5",
    "score": 32,
    "keywords": [
      "하수처리",
      "수처리",
      "방류수",
      "하수처리장"
    ],
    "domestic": true,
    "region": "domestic",
    "source_type": "search_rss"
  },
  {
    "date": "2026-05-26",
    "title": "\"버려지던 하수 방류수가 전기로\", 서산시, 공공하수처리장에 '친환경 소수력 발전' 도입 - v.daum.net",
    "ko_title": "서산시, 하수 방류수로 친환경 발전 도입",
    "brief": "서산시가 공공하수처리장에서 하수 방류수를 활용한 친환경 소수력 발전을 도입했습니다. 이는 하수 처리 과정에서 발생하는 자원을 효율적으로 활용하는 사례로 주목받고 있습니다.",
    "summary": "서산시는 공공하수처리장에서 버려지던 하수 방류수를 이용해 친환경 소수력 발전을 도입했습니다. 이 프로젝트는 하수 처리 과정에서 발생하는 자원을 활용하여 전기를 생산하는 혁신적인 접근 방식입니다. 이는 수처리 산업에서 자원의 재이용을 촉진하고, 지속 가능한 에너지 생산에 기여할 수 있는 사례로 평가됩니다. 하수 방류수의 활용은 환경 보호와 에너지 효율성을 동시에 달성할 수 있는 중요한 발전 방향입니다.",
    "why_important": "이 프로젝트는 하수 처리 과정에서 자원의 재이용을 통해 에너지 효율성을 높이는 데 기여합니다. 이는 수처리 산업의 지속 가능성을 강화하는 중요한 사례로, 향후 유사한 프로젝트의 확산을 촉진할 수 있습니다.",
    "category": "재이용수",
    "countries": [
      "대한민국"
    ],
    "companies": [],
    "technologies": [
      "소수력 발전",
      "하수처리"
    ],
    "policy_alert": "",
    "source": "Google News Korea 재이용수 PFAS",
    "link": "https://news.google.com/rss/articles/CBMiT0FVX3lxTFB3SGdHN2N4aXpOTll5OW1VcnFBd1dWMTlVekpkQVR4ZkNoaVF5VmVUVTZxNXJUX3o4NnBaOU5razVvMUhlUXQ1TlNCOWlsTWM?oc=5",
    "score": 32,
    "keywords": [
      "하수처리",
      "수처리",
      "방류수",
      "하수처리장"
    ],
    "domestic": true,
    "region": "domestic",
    "source_type": "search_rss"
  },
  {
    "date": "2026-04-27",
    "title": "Lower-biofouling ultrafiltration membrane module - FloralDaily",
    "ko_title": "저생물오염 초여과막 모듈 개발",
    "brief": "저생물오염 초여과막 모듈이 개발되었습니다. 이 기술은 수처리 효율성을 높이는 데 기여할 것으로 기대됩니다.",
    "summary": "최근 저생물오염 초여과막 모듈이 개발되었습니다. 이 모듈은 생물오염을 줄여 수처리 효율성을 높이는 데 도움을 줄 것으로 보입니다. 수처리 산업에서 초여과막 기술은 중요한 역할을 하며, 이러한 혁신은 시장 경쟁력을 강화할 수 있습니다. 또한, 이 기술은 다양한 산업 분야에서의 적용 가능성을 열어줄 것입니다.",
    "why_important": "이 기술은 수처리 효율성을 높여 시장 경쟁력을 강화할 수 있습니다. 또한, 생물오염 문제를 해결하는 데 기여할 것으로 예상됩니다.",
    "category": "분리막/MBR",
    "countries": [],
    "companies": [],
    "technologies": [
      "ultrafiltration",
      "biofouling",
      "membrane"
    ],
    "policy_alert": "",
    "source": "Google News Global Membrane MBR",
    "link": "https://news.google.com/rss/articles/CBMimAFBVV95cUxOeEE5X1prUmNNRG1CaHFMdDA5Z2xQbWxiV2JscDFhMi1XNTZkdExFbV9sVkpPNmEyc2E0X2pzaUdCcEp0VFlXckp3cmpmcktTWEFjZU4ySmpteUc5T2VPWmZLTU1YdFV1YWtUT0NZZG95V3R3NkJkV2RaVWxXRGU5Z2NGWXMxbF9jMm9iUW5OMHVyUnotVlRMQQ?oc=5",
    "score": 32,
    "keywords": [
      "membrane",
      "ultrafiltration",
      "biofouling",
      "membrane module"
    ],
    "domestic": false,
    "region": "global",
    "source_type": "search_rss"
  },
  {
    "date": "2025-08-04",
    "title": "Deciphering nitrogen-driven microbial succession in an anaerobic membrane bioreactor-coupled A - Nature",
    "ko_title": "혐기성 막 생물 반응기에서 질소 주도 미생물 변화 분석",
    "brief": "혐기성 막 생물 반응기에서 질소에 의해 주도되는 미생물 변화에 대한 연구가 진행되었습니다. 이 연구는 수처리 산업에 중요한 통찰을 제공합니다.",
    "summary": "최근 연구에서는 혐기성 막 생물 반응기에서 질소가 미생물 군집의 변화를 어떻게 유도하는지를 분석했습니다. 이 연구는 질소가 미생물의 다양성과 기능에 미치는 영향을 규명하며, 수처리 공정의 효율성을 높이는 데 기여할 수 있습니다. 특히, 질소 제거 과정에서의 미생물 상호작용이 강조되었습니다. 이러한 발견은 수처리 산업에서의 막 기술의 발전과 관련이 깊습니다.",
    "why_important": "이 연구는 수처리 공정에서 질소 제거의 중요성을 강조하며, 효율적인 수처리 기술 개발에 기여할 수 있습니다. 시장에서는 질소 제거 기술의 수요가 증가하고 있으며, 이는 규제와 기술 발전에 중요한 영향을 미칠 것입니다.",
    "category": "분리막/MBR",
    "countries": [],
    "companies": [],
    "technologies": [
      "membrane bioreactor",
      "membrane",
      "nitrogen"
    ],
    "policy_alert": "",
    "source": "Google News Global Membrane MBR",
    "link": "https://news.google.com/rss/articles/CBMiX0FVX3lxTE9SeDRWcDYtSzY1R1BPd2xIVHI4Wk5Xc01aNGFGOWZOTFcyUFEyR3BEcklXdFh2QUZ3ZHZhcFpWV29ENC03bk1MVGdqNzVMTlhnWUdaa205b25LWDJjMUFr?oc=5",
    "score": 29,
    "keywords": [
      "membrane bioreactor",
      "membrane",
      "nitrogen",
      "cip"
    ],
    "domestic": false,
    "region": "global",
    "source_type": "search_rss"
  },
  {
    "date": "2025-04-15",
    "title": "Release of microplastics from polymeric ultrafiltration membrane system for drinking water treatment under different operating conditions - ScienceDirect.com",
    "ko_title": "음용수 처리에서 미세플라스틱 방출 연구",
    "brief": "폴리머 초여과막 시스템에서 음용수 처리 시 미세플라스틱 방출에 대한 연구가 진행되었습니다. 다양한 운영 조건에서의 결과가 분석되었습니다.",
    "summary": "최근 연구에서는 폴리머 초여과막 시스템이 음용수 처리 과정에서 미세플라스틱을 방출하는지에 대한 실험이 수행되었습니다. 다양한 운영 조건에서의 미세플라스틱 방출량이 측정되었으며, 이는 수처리 산업에 중요한 영향을 미칠 수 있습니다. 특히, 음용수의 안전성과 품질 보장 측면에서 이 연구는 중요한 기초 자료를 제공합니다. 이러한 연구 결과는 향후 수처리 기술 개발 및 규제 정책 수립에 기여할 것으로 기대됩니다.",
    "why_important": "이 연구는 음용수의 안전성을 확보하기 위한 기술적 도전 과제를 제시합니다. 수처리 산업에서 미세플라스틱 문제는 규제 및 기술 개발의 중요한 이슈로 부각되고 있습니다.",
    "category": "분리막/MBR",
    "countries": [],
    "companies": [],
    "technologies": [
      "membrane",
      "ultrafiltration",
      "water treatment",
      "drinking water"
    ],
    "policy_alert": "",
    "source": "Google News Global Membrane MBR",
    "link": "https://news.google.com/rss/articles/CBMie0FVX3lxTE1IRkVXSGRXQXlUbGgxcnNvWFQ1NkdLVkpXMGxHRlp3VUdibnFxU1ZGYU0zaDRMLXh4VFVtcVU4aUU3d3JzVE9ZVjVTTHpOcWw0ZXk4TlhMVDhmeTJDZXRfZWwtRmV3LTEyeG01NWNxS0JCQXozQ2E0Yk01TQ?oc=5",
    "score": 28,
    "keywords": [
      "membrane",
      "ultrafiltration",
      "water treatment",
      "drinking water"
    ],
    "domestic": false,
    "region": "global",
    "source_type": "search_rss"
  },
  {
    "date": "2024-06-19",
    "title": "A comparison of typical ultrafiltration processes in drinking water treatment: Implications for fouling control and disinfection performance - ScienceDirect.com",
    "ko_title": "음용수 처리에서의 초여과 공정 비교",
    "brief": "음용수 처리에서 초여과 공정의 비교가 이루어졌습니다. 오염 방지와 소독 성능에 대한 시사점을 제공합니다.",
    "summary": "이 연구는 음용수 처리에서의 전형적인 초여과 공정을 비교하고, 오염 방지 및 소독 성능에 대한 시사점을 제시합니다. 초여과 기술은 수처리 산업에서 중요한 역할을 하며, 특히 물의 품질을 유지하는 데 필수적입니다. 연구 결과는 수처리 공정의 효율성을 높이는 데 기여할 수 있습니다. 또한, 이러한 기술은 향후 물 부족 문제 해결에도 기여할 것으로 기대됩니다.",
    "why_important": "초여과 기술은 수처리 산업의 핵심 기술로, 물의 품질을 향상시키는 데 중요한 역할을 합니다. 이는 시장에서의 경쟁력을 높이고, 규제 준수에 기여할 수 있습니다.",
    "category": "분리막/MBR",
    "countries": [],
    "companies": [],
    "technologies": [
      "ultrafiltration",
      "water treatment"
    ],
    "policy_alert": "",
    "source": "Google News Global Membrane MBR",
    "link": "https://news.google.com/rss/articles/CBMie0FVX3lxTE9tYW55YjZZd0xPRC15M1dYQ0NQSmpYcm5rUHUyekc4NVdBcjlnT1JWS2FtTVJSamYxRWozaEYyRG9PZkxpaUVFc0FnVTBlYWV1eVl4U1U3SnUxYW9CQjB0cDB4SGFqQ1MtcTlRcXd4Tld5Qk1SRzhuSURSOA?oc=5",
    "score": 28,
    "keywords": [
      "ultrafiltration",
      "water treatment",
      "drinking water",
      "fouling control"
    ],
    "domestic": false,
    "region": "global",
    "source_type": "search_rss"
  },
  {
    "date": "2015-08-05",
    "title": "[글로벌수처리기술] 새로운 막여과 설비 개발로 물재이용 공정 활성화 - 워터저널",
    "ko_title": "막여과 설비 개발로 물재이용 공정 활성화",
    "brief": "새로운 막여과 설비가 개발되어 물재이용 공정이 활성화되고 있습니다. 이는 수처리 산업에 긍정적인 영향을 미칠 것으로 기대됩니다.",
    "summary": "최근 새로운 막여과 설비가 개발되면서 물재이용 공정이 활성화되고 있습니다. 이 기술은 수처리 산업의 효율성을 높이고, 자원의 재활용을 촉진하는 데 기여할 것으로 보입니다. 막여과 기술은 오염물질 제거에 효과적이며, 다양한 산업 분야에서 활용될 수 있습니다. 이러한 발전은 지속 가능한 물 관리와 환경 보호에 중요한 역할을 할 것입니다.",
    "why_important": "이 기술의 발전은 물 재이용 시장의 성장에 기여할 것으로 예상됩니다. 또한, 규제 강화와 환경 보호의 필요성에 부응하는 기술적 진보로 볼 수 있습니다.",
    "category": "막여과/MBR",
    "countries": [],
    "companies": [],
    "technologies": [
      "막여과",
      "물재이용"
    ],
    "policy_alert": "",
    "source": "Google News Korea 막여과 MBR",
    "link": "https://news.google.com/rss/articles/CBMickFVX3lxTE9QX1hiUmNOaXVqcTkxLUhqY2ctMEg3OW1wR25faHJOaU44cHpqRi1SOVFYaEVZcEp5SGY3Ul9rNlV2aHlpYm40UTFISHJFZFhBc2xIQjVRUFRPQXFsdEtEV2ROZ3gxcUZjd2V2aFc0X2pIZ9IBdkFVX3lxTE1pc292M2p0TUtTUWZnQzB3MXlJTE1LQTU5MHROWktORU80VEhaaFoyZmF5REtLUTRqb3RqakZSSXJrT2dPZW85TUdBRTFSQTNMajA4MjdjcTlqeHZjczBYWXpzenFSRk5iNHgtekx6YmI3WWpGUWc?oc=5",
    "score": 27,
    "keywords": [
      "수처리",
      "막여과",
      "물재이용"
    ],
    "domestic": true,
    "region": "domestic",
    "source_type": "search_rss"
  },
  {
    "date": "2026-06-02",
    "title": "‘악취 없애고 쾌적하게’...북항하수처리장 정비 실시 - 전남타임스",
    "ko_title": "북항하수처리장 정비로 쾌적한 환경 조성",
    "brief": "북항하수처리장이 정비를 통해 악취 문제를 해결하고 쾌적한 환경을 조성합니다. 이는 지역 주민들에게 긍정적인 영향을 미칠 것으로 기대됩니다.",
    "summary": "북항하수처리장은 최근 정비 작업을 통해 악취 문제를 해결하고 쾌적한 환경을 조성하기 위한 노력을 하고 있습니다. 이 정비는 하수처리 시설의 효율성을 높이고, 지역 주민들의 생활 환경을 개선하는 데 기여할 것으로 보입니다. 수처리 산업에서는 이러한 정비 작업이 하수처리 기술의 발전과 관련이 있으며, 지역 사회의 수질 개선에도 긍정적인 영향을 미칠 것입니다. 향후 이러한 정비 사례가 다른 지역으로 확산될 가능성도 있습니다.",
    "why_important": "이 정비는 지역 주민의 생활 환경 개선과 직결되어 있어 사회적 반향을 일으킬 수 있습니다. 수처리 기술의 발전과 함께 하수처리 시설의 효율성을 높이는 것은 지속 가능한 수자원 관리에 중요한 요소입니다.",
    "category": "수처리 산업동향",
    "countries": [
      "대한민국"
    ],
    "companies": [],
    "technologies": [
      "하수처리"
    ],
    "policy_alert": "",
    "source": "Google News Korea 상하수도",
    "link": "https://news.google.com/rss/articles/CBMiZkFVX3lxTE1ZZ2dxUFFxT1h2cWU5RzRFamxLd1JKSnloM2dSRWhhZWhjRWpaWGxGVXk2blJzX1dUT2Y4bjVtQ3V5cUdCaXRGWmNjbnpyOXUxeDZqTm9HYU93UGdrMkpkMU5YdW1adw?oc=5",
    "score": 26,
    "keywords": [
      "하수처리",
      "수처리",
      "하수처리장"
    ],
    "domestic": true,
    "region": "domestic",
    "source_type": "search_rss"
  },
  {
    "date": "2026-05-28",
    "title": "전주시, 하수처리장 434억 들여 새 단장…안정적 운영 총력 - 연합뉴스",
    "ko_title": "전주시, 하수처리장 434억 들여 새 단장",
    "brief": "전주시는 하수처리장에 434억 원을 투자해 시설을 새롭게 단장하고 있습니다. 이는 안정적인 운영을 위한 노력의 일환입니다.",
    "summary": "전주시는 하수처리장에 434억 원을 투자하여 시설을 현대화하고 안정적인 운영을 목표로 하고 있습니다. 이번 프로젝트는 하수처리 효율성을 높이고, 지역 주민의 환경 개선에 기여할 것으로 기대됩니다. 하수처리 산업은 지속 가능한 도시 발전에 필수적인 요소로, 이러한 투자는 지역 사회의 수질 개선에 중요한 역할을 할 것입니다. 전주시의 이 같은 노력은 다른 지역에도 긍정적인 영향을 미칠 수 있습니다.",
    "why_important": "하수처리장 현대화는 지역 환경 개선과 수질 관리에 중요한 영향을 미칩니다. 이는 수처리 산업의 발전과 관련된 프로젝트로, 향후 유사한 투자가 다른 지역에서도 이루어질 가능성이 있습니다.",
    "category": "프로젝트/수주",
    "countries": [
      "대한민국"
    ],
    "companies": [],
    "technologies": [
      "하수처리"
    ],
    "policy_alert": "",
    "source": "Google News Korea 상하수도",
    "link": "https://news.google.com/rss/articles/CBMiW0FVX3lxTE10VTZaZ0JKUTBaR2dnRnRRc0psUGRZOTRPMUtxME1tcnlScmM2Z0VmQ1NKY0RseUlaSlpMenhtcVc3Zkd4cFA5aGl1QWdVWFpKbENrQkZPVGNpXzTSAWBBVV95cUxOTkFpMmhyNGpqWkhNZzNvZUZNWEpYNXFQX1ByT3l3Q2huY3l5b2dzS2tHUGxOMDdkMnFyTjlwYmtJMHR6cHpOdkg0d0dyVl9wZjc1bjB4ZVdWSFNZaWpMS1Y?oc=5",
    "score": 26,
    "keywords": [
      "하수처리",
      "수처리",
      "하수처리장"
    ],
    "domestic": true,
    "region": "domestic",
    "source_type": "search_rss"
  },
  {
    "date": "2026-05-29",
    "title": "익산시 하수처리장, 어린이 환경교육 체험공간으로 - 전북엔비전",
    "ko_title": "익산시 하수처리장, 어린이 환경교육 공간으로",
    "brief": "익산시 하수처리장이 어린이 환경교육 체험공간으로 변모합니다. 이 initiative는 어린이들에게 환경 보호의 중요성을 알리는 데 기여할 것입니다.",
    "summary": "익산시는 하수처리장을 어린이 환경교육 체험공간으로 조성하기로 결정했습니다. 이 프로젝트는 어린이들에게 수처리 과정과 환경 보호의 중요성을 교육하는 기회를 제공합니다. 하수처리장은 지역 사회의 환경 교육의 중심지로 자리 잡을 것으로 기대됩니다. 이러한 변화는 수처리 산업의 사회적 책임을 강조하는 사례로 볼 수 있습니다.",
    "why_important": "이 프로젝트는 어린이들에게 환경 교육을 제공함으로써 미래 세대의 환경 의식을 높이는 데 기여할 것입니다. 수처리 산업의 사회적 역할이 강화되는 중요한 사례로, 향후 유사한 프로젝트가 증가할 가능성이 있습니다.",
    "category": "수처리 산업동향",
    "countries": [
      "대한민국"
    ],
    "companies": [],
    "technologies": [
      "하수처리",
      "수처리"
    ],
    "policy_alert": "",
    "source": "Google News Korea 상하수도",
    "link": "https://news.google.com/rss/articles/CBMiZkFVX3lxTFA3azJsT2dQN3IteW8zNGgwZVVMYmx3dXJCOVhzcFN6NURpRzN6SHJMY05QdTdYRkRMM2czdG5WRHIyR09TY3RDX2ZUUWxhVFNsUHNFSnIzTzNZM0JpYlFBVDM3dVYzQQ?oc=5",
    "score": 26,
    "keywords": [
      "하수처리",
      "수처리",
      "하수처리장"
    ],
    "domestic": true,
    "region": "domestic",
    "source_type": "search_rss"
  },
  {
    "date": "2026-05-30",
    "title": "안성시, 하수처리장 집중 안전 점검 추진 - 자치안성신문",
    "ko_title": "안성시, 하수처리장 안전 점검 추진",
    "brief": "안성시가 하수처리장에 대한 집중 안전 점검을 실시합니다. 이는 수처리 시설의 안전성을 높이기 위한 조치입니다.",
    "summary": "안성시는 하수처리장의 안전성을 확보하기 위해 집중 안전 점검을 추진한다고 발표했습니다. 이번 점검은 하수처리 시설의 운영 상태와 안전 기준 준수 여부를 확인하기 위한 것입니다. 하수처리장은 지역의 수질 관리와 환경 보호에 중요한 역할을 하므로, 이러한 점검은 수처리 산업에 긍정적인 영향을 미칠 것으로 예상됩니다. 안전 점검을 통해 시설의 문제를 조기에 발견하고 개선할 수 있는 기회를 제공합니다.",
    "why_important": "하수처리장의 안전 점검은 지역 주민의 건강과 환경 보호에 필수적입니다. 이는 수처리 산업의 신뢰성을 높이고, 향후 규제 강화에 대비하는 중요한 조치입니다.",
    "category": "규제/정책",
    "countries": [
      "대한민국"
    ],
    "companies": [],
    "technologies": [
      "하수처리"
    ],
    "policy_alert": "하수처리장 안전 점검 강화에 대한 정책이 시행될 예정입니다.",
    "source": "Google News Korea 상하수도",
    "link": "https://news.google.com/rss/articles/CBMifEFVX3lxTE45OXZ4R0FDWElvSjN4UUNvTlo3MEt0azV6eHphbVM5bmpENU0za29teXVfMWRCOWdhbFRkYmdmaGVIRGpzT3RmcnlIYU16WlBXSlVQWGR2azE1NXNUMS1hSnlFU1ZMalhPZG50RTN1Mkg5SVJHWlZweUMwaHk?oc=5",
    "score": 26,
    "keywords": [
      "하수처리",
      "수처리",
      "하수처리장"
    ],
    "domestic": true,
    "region": "domestic",
    "source_type": "search_rss"
  },
  {
    "date": "2026-05-28",
    "title": "전주시, 노후 공공하수처리장 대수선 추진 - v.daum.net",
    "ko_title": "전주시, 노후 공공하수처리장 대수선 추진",
    "brief": "전주시는 노후된 공공하수처리장의 대수선 계획을 발표했습니다. 이는 지역 환경 개선과 수질 향상을 목표로 하고 있습니다.",
    "summary": "전주시는 노후된 공공하수처리장을 대수선하기로 결정했습니다. 이 프로젝트는 지역 주민의 생활환경을 개선하고, 하수 처리 효율성을 높이는 것을 목표로 하고 있습니다. 하수처리 시설의 현대화는 수처리 산업에 긍정적인 영향을 미칠 것으로 예상됩니다. 또한, 이러한 대수선은 지역 내 수질 개선에도 기여할 것입니다.",
    "why_important": "이 프로젝트는 지역 환경 개선과 수질 향상에 기여할 것으로 보입니다. 수처리 시설의 현대화는 향후 유사한 프로젝트의 모델이 될 수 있습니다.",
    "category": "프로젝트/수주",
    "countries": [
      "대한민국"
    ],
    "companies": [],
    "technologies": [
      "하수처리"
    ],
    "policy_alert": "",
    "source": "Google News Korea 상하수도",
    "link": "https://news.google.com/rss/articles/CBMiT0FVX3lxTFBlNnF4N1FnOEZXTmpKOUs0bzZjVmZzekxTY0RydTNkZ21yMkhRRFVYRjJ3VGFQWTQ2VHRkY3ZkMl9aZHdZUW1qcjRjRnQxeFU?oc=5",
    "score": 26,
    "keywords": [
      "하수처리",
      "수처리",
      "하수처리장"
    ],
    "domestic": true,
    "region": "domestic",
    "source_type": "search_rss"
  },
  {
    "date": "2026-05-28",
    "title": "한화 시공 천안하수처리장, 공기연장 놓고 특혜 공방 - v.daum.net",
    "ko_title": "한화 시공 천안하수처리장, 공기연장 놓고 특혜 공방",
    "brief": "한화가 시공 중인 천안하수처리장에서 공기연장 문제로 특혜 논란이 일고 있다. 이 사건은 수처리 산업의 공정성과 투명성에 대한 우려를 불러일으킨다.",
    "summary": "천안하수처리장에서 한화의 공기연장 요청이 특혜 논란을 일으키고 있다. 이 사건은 하수처리 시설의 시공 과정에서의 공정성 문제를 드러내며, 수처리 산업의 투명성에 대한 우려를 낳고 있다. 하수처리장은 지역 사회의 환경 관리에 중요한 역할을 하며, 이러한 논란은 향후 프로젝트에 영향을 미칠 수 있다. 따라서, 이 사건은 수처리 산업의 신뢰성에 중대한 영향을 미칠 수 있다.",
    "why_important": "이 사건은 수처리 산업의 공정성과 투명성을 강조하며, 향후 프로젝트 수주에 영향을 미칠 수 있습니다. 규제 기관의 감시 강화가 예상되므로, 업계의 대응이 필요할 것으로 보입니다.",
    "category": "프로젝트/수주",
    "countries": [
      "대한민국"
    ],
    "companies": [
      "한화"
    ],
    "technologies": [
      "하수처리"
    ],
    "policy_alert": "",
    "source": "Google News Korea 상하수도",
    "link": "https://news.google.com/rss/articles/CBMiT0FVX3lxTFB1S2REM3M2cThDZ0RkMlJDNkxTZDVkUkhyZllNamg1M3Rvb1JsTFdGSWx3TkpFbEtQWW5uVS1OeVhzOVZqaUZwa0hsVjJja2s?oc=5",
    "score": 26,
    "keywords": [
      "하수처리",
      "수처리",
      "하수처리장"
    ],
    "domestic": true,
    "region": "domestic",
    "source_type": "search_rss"
  },
  {
    "date": "2026-05-31",
    "title": "익산시 공공하수처리장, 어린이 친화적 환경교육 체험 공간으로 새단장 > 뉴스 - 더코리아",
    "ko_title": "익산시 하수처리장, 어린이 환경교육 공간으로 변신",
    "brief": "익산시 공공하수처리장이 어린이 친화적인 환경교육 체험 공간으로 새단장했습니다. 이는 지역 사회의 환경 인식을 높이는 데 기여할 것으로 기대됩니다.",
    "summary": "익산시는 공공하수처리장을 어린이 친화적인 환경교육 체험 공간으로 새롭게 단장했습니다. 이 공간은 어린이들이 수처리 과정을 배우고 환경 보호의 중요성을 이해할 수 있도록 설계되었습니다. 이러한 변화는 지역 사회의 환경 인식을 높이고, 미래 세대의 지속 가능한 발전을 위한 교육적 기회를 제공합니다. 수처리 산업과의 연계성을 통해 하수처리장의 역할이 단순한 처리 시설을 넘어 교육적 기능을 수행하게 됩니다.",
    "why_important": "이러한 변화는 지역 사회의 환경 교육을 강화하고, 어린이들에게 수처리의 중요성을 알리는 데 기여합니다. 이는 수처리 산업의 사회적 책임을 강조하는 중요한 사례로, 향후 유사한 프로젝트가 증가할 가능성이 있습니다.",
    "category": "프로젝트/수주",
    "countries": [
      "한국"
    ],
    "companies": [],
    "technologies": [
      "하수처리",
      "환경교육"
    ],
    "policy_alert": "",
    "source": "Google News Korea 상하수도",
    "link": "https://news.google.com/rss/articles/CBMicEFVX3lxTFBzczRSZG9LQTd5dEYxajF2VGQxMFNYM05MZEx3ZENnc3E3VE5xMXNkRFRMdHVBOVpMakhrdEJwb0JqejR0MEtKMGY5X1RwY2RVQ2NraTRzR1cxNmdWM1NLWU1paGZNbXBQb3U3NlBmVG0?oc=5",
    "score": 26,
    "keywords": [
      "하수처리",
      "수처리",
      "하수처리장"
    ],
    "domestic": true,
    "region": "domestic",
    "source_type": "search_rss"
  },
  {
    "date": "2026-05-28",
    "title": "전주시 하수처리장 운영관리 집중 - 전라일보",
    "ko_title": "전주시 하수처리장 운영관리 집중",
    "brief": "전주시는 하수처리장 운영관리에 집중하고 있습니다. 이는 지역 수처리 효율성을 높이기 위한 노력으로 보입니다.",
    "summary": "전주시는 하수처리장 운영관리에 집중하고 있으며, 이는 지역 내 수처리 효율성을 높이기 위한 전략의 일환입니다. 하수처리장은 도시의 환경 보호와 공공 건강을 위해 필수적인 시설로, 운영 관리의 중요성이 강조되고 있습니다. 이러한 노력은 수처리 산업의 발전과 지속 가능성을 높이는 데 기여할 것으로 예상됩니다. 전주시는 향후 하수처리장 운영의 최적화를 통해 지역 주민들에게 더 나은 서비스를 제공할 계획입니다.",
    "why_important": "하수처리장 운영 관리는 지역 환경과 공공 건강에 직접적인 영향을 미칩니다. 이는 수처리 산업의 효율성을 높이고, 지속 가능한 발전을 위한 중요한 요소입니다.",
    "category": "수처리 산업동향",
    "countries": [
      "대한민국"
    ],
    "companies": [],
    "technologies": [
      "하수처리"
    ],
    "policy_alert": "",
    "source": "Google News Korea 상하수도",
    "link": "https://news.google.com/rss/articles/CBMibEFVX3lxTE9uY1RhTE5tbno4bTdwcUw3Z0pHWk5jZ0dlVFRPRGxsXzdjQTdDNS1QT0hFdnBlX28xMGktZHlRZHRBRXNsVjJWNnhYSDNDLVpERF92V0hpVXU4LU5aSHg2WllZSGdmMkxwM0dwWdIBcEFVX3lxTE9HV3o4SXBqUjY1RWx2RHpBbEdyVnh0Wl9HOUNNZGlXdUhXRW1RNURuOUtPOXhHNjV4N0hsc1pmQzh6cHV2OWhVWDl0dGNrZVF1eDV4OUtQSXRKeXN0VDBpdk5RSFZPNmVBWEFSUl93V2U?oc=5",
    "score": 26,
    "keywords": [
      "하수처리",
      "수처리",
      "하수처리장"
    ],
    "domestic": true,
    "region": "domestic",
    "source_type": "search_rss"
  },
  {
    "date": "2026-05-27",
    "title": "기획처, 하수처리장 에너지 자립화 확산 추진…내년 예산 반영 검토 - v.daum.net",
    "ko_title": "하수처리장 에너지 자립화 추진, 내년 예산 검토",
    "brief": "기획처가 하수처리장 에너지 자립화 확산을 추진하고 있습니다. 내년 예산에 반영할 계획을 검토 중입니다.",
    "summary": "기획재정부는 하수처리장의 에너지 자립화를 위한 정책을 추진하고 있으며, 이를 내년 예산에 반영할 계획을 검토하고 있습니다. 하수처리장은 에너지 소비가 큰 시설로, 자립화는 운영 비용 절감과 환경적 지속 가능성을 높이는 데 기여할 수 있습니다. 이러한 정책은 수처리 산업의 혁신과 효율성을 증대시키는 데 중요한 역할을 할 것으로 기대됩니다. 에너지 자립화는 하수처리장의 운영 효율성을 높이고, 탄소 배출 감소에도 기여할 수 있습니다.",
    "why_important": "하수처리장의 에너지 자립화는 운영 비용 절감과 환경적 지속 가능성을 높이는 데 중요합니다. 이는 수처리 산업의 혁신과 효율성을 증대시키는 데 기여할 것으로 예상됩니다.",
    "category": "수처리 산업동향",
    "countries": [
      "대한민국"
    ],
    "companies": [],
    "technologies": [
      "하수처리",
      "에너지 자립화"
    ],
    "policy_alert": "하수처리장 에너지 자립화 관련 정책이 내년 예산에 반영될 가능성이 있습니다.",
    "source": "Google News Korea 상하수도",
    "link": "https://news.google.com/rss/articles/CBMiT0FVX3lxTE9mQ3VNdU1tZjdKVTRXVEdBamZNcWR2VWF5eTk2TURSeldqbUVlUEY2aDdwZEJqQTRCOUE3bnU5QXdFQnpmMmxsNTVzN3ZkOU0?oc=5",
    "score": 26,
    "keywords": [
      "하수처리",
      "수처리",
      "하수처리장"
    ],
    "domestic": true,
    "region": "domestic",
    "source_type": "search_rss"
  },
  {
    "date": "2026-05-20",
    "title": "여천하수처리장 본격 추진…환경평가 착수 - v.daum.net",
    "ko_title": "여천하수처리장 본격 추진…환경평가 착수",
    "brief": "여천하수처리장이 본격적으로 추진되며 환경평가에 착수했습니다. 이는 지역의 수처리 인프라 개선에 기여할 것으로 기대됩니다.",
    "summary": "여천하수처리장이 본격적으로 추진되며 환경평가가 시작되었습니다. 이 프로젝트는 지역 내 하수처리 능력을 향상시키고, 환경 보호를 위한 중요한 단계로 평가됩니다. 하수처리장은 지역 주민의 생활 환경 개선에 기여할 것으로 보입니다. 수처리 산업에 있어 이러한 프로젝트는 인프라 확충과 기술 발전의 기회를 제공합니다.",
    "why_important": "이 프로젝트는 지역 수처리 인프라의 개선을 통해 환경 보호에 기여할 수 있습니다. 이는 수처리 시장의 성장과 관련된 중요한 발전입니다.",
    "category": "프로젝트/수주",
    "countries": [],
    "companies": [],
    "technologies": [
      "하수처리"
    ],
    "policy_alert": "",
    "source": "Google News Korea 상하수도",
    "link": "https://news.google.com/rss/articles/CBMiT0FVX3lxTE9fWUx4UUZjRkZocWNZNkxWTUJNODQ4UEk2aldnbFJ4QmR5WFhxU0hvOGhrVUZuak9icVlZUGZEcjZJZWRFU0tNa1lXaGZrYkU?oc=5",
    "score": 26,
    "keywords": [
      "하수처리",
      "수처리",
      "하수처리장"
    ],
    "domestic": true,
    "region": "domestic",
    "source_type": "search_rss"
  },
  {
    "date": "2026-05-21",
    "title": "[경주시] 강동 대촌 소규모하수처리장 증설 마무리 추진 - 워터저널",
    "ko_title": "경주시, 강동 대촌 하수처리장 증설 마무리",
    "brief": "경주시가 강동 대촌 소규모 하수처리장 증설을 마무리하고 있습니다. 이번 증설은 지역 하수 처리 능력을 향상시키기 위한 조치입니다.",
    "summary": "경주시는 강동 대촌 소규모 하수처리장 증설을 완료할 예정입니다. 이 프로젝트는 지역 내 하수 처리 용량을 증가시키고, 환경 보호를 위한 중요한 조치로 평가받고 있습니다. 하수처리장 증설은 지역 주민의 생활 환경 개선에 기여할 것으로 기대됩니다. 수처리 산업의 발전과 관련하여, 이러한 시설의 증설은 지속 가능한 수자원 관리에 중요한 역할을 할 것입니다.",
    "why_important": "이번 증설은 지역 하수 처리 능력을 향상시켜 환경 보호에 기여할 것입니다. 이는 수처리 산업의 발전과 관련된 중요한 프로젝트로, 향후 유사한 프로젝트의 추진에 긍정적인 영향을 미칠 것으로 보입니다.",
    "category": "프로젝트/수주",
    "countries": [
      "대한민국"
    ],
    "companies": [],
    "technologies": [
      "하수처리"
    ],
    "policy_alert": "",
    "source": "Google News Korea 상하수도",
    "link": "https://news.google.com/rss/articles/CBMickFVX3lxTE1ibm5vcjBlUGhoTDBmeFctSHd5TTY2MkFEaHJ5WVp3Ui1WV00tSm5Jd1ZITmhrZzdsRnE3MHNqOHN1ckNoek83OG90RGYzQ2ItR3JTV2RwWUJqTXo2b2t3cmJKLXhJU3lWUE5MYjZzSHZZZ9IBdkFVX3lxTE9Pd09wS2tpYWpBRlJTQ1hSZ1h5WVBRZEFWSDlHVFFsaUhpSkdwZ1ZpY0x3Wlo1MjdTUEV5UjJqRms0aHdDNVF5Z2VPZHdETXh0T29xbjFtNmdEVXZQSFJzUURBYUY0TTdFeFNzZG8td2tlcXNBZ2c?oc=5",
    "score": 26,
    "keywords": [
      "하수처리",
      "수처리",
      "하수처리장"
    ],
    "domestic": true,
    "region": "domestic",
    "source_type": "search_rss"
  },
  {
    "date": "2026-05-20",
    "title": "여천하수처리장 본격 추진…환경평가 착수 - KBS 뉴스",
    "ko_title": "여천하수처리장 본격 추진…환경평가 착수",
    "brief": "여천하수처리장이 본격적으로 추진되며 환경평가에 착수했습니다. 이는 지역의 수처리 인프라 개선에 기여할 것으로 기대됩니다.",
    "summary": "여천하수처리장이 본격적으로 추진되며 환경평가가 시작되었습니다. 이 프로젝트는 지역 내 하수처리 용량을 증대시키고, 수질 개선에 기여할 것으로 예상됩니다. 하수처리장은 지역 주민의 생활환경을 개선하고, 지속 가능한 수처리 시스템 구축에 중요한 역할을 할 것입니다. 이러한 프로젝트는 한국의 수처리 산업에 긍정적인 영향을 미칠 것으로 보입니다.",
    "why_important": "이 프로젝트는 지역의 수처리 인프라를 개선하여 환경 규제를 준수하는 데 중요한 역할을 할 것입니다. 이는 향후 유사한 프로젝트의 추진에 긍정적인 선례가 될 수 있습니다.",
    "category": "프로젝트/수주",
    "countries": [
      "한국"
    ],
    "companies": [],
    "technologies": [
      "하수처리"
    ],
    "policy_alert": "",
    "source": "Google News Korea 상하수도",
    "link": "https://news.google.com/rss/articles/CBMiW0FVX3lxTE1hLVhCTjhJbnd2SXNBa2NqeXg5MVZEUnNhNVh3SFpvU2Rkc3ZqcGpHUEJad01VeUdlbDlEUWhyQ2JMTzRLdzg4WlFUVXRvbGUwZ2Zfa2w1RE9tYmM?oc=5",
    "score": 26,
    "keywords": [
      "하수처리",
      "수처리",
      "하수처리장"
    ],
    "domestic": true,
    "region": "domestic",
    "source_type": "search_rss"
  },
  {
    "date": "2026-05-13",
    "title": "안성시, 하수처리장 집중 안전점검 - 환경일보",
    "ko_title": "안성시, 하수처리장 집중 안전점검 실시",
    "brief": "안성시가 하수처리장에 대한 집중 안전점검을 실시합니다. 이번 점검은 하수처리 시설의 안전성을 높이기 위한 조치입니다.",
    "summary": "안성시는 하수처리장의 안전성을 확보하기 위해 집중 안전점검을 실시한다고 발표했습니다. 이번 점검은 하수처리 시설의 운영 상태와 안전 기준 준수 여부를 확인하기 위한 것입니다. 하수처리장은 수처리 산업에서 중요한 역할을 하며, 안전한 운영은 환경 보호와 직결됩니다. 이러한 점검은 지역 주민의 건강과 안전을 보장하는 데 기여할 것으로 기대됩니다.",
    "why_important": "하수처리장의 안전 점검은 지역 주민의 건강과 환경 보호에 필수적입니다. 이는 수처리 산업의 신뢰성을 높이고, 향후 규제 강화에 대비하는 중요한 조치입니다.",
    "category": "규제/정책",
    "countries": [
      "대한민국"
    ],
    "companies": [],
    "technologies": [
      "하수처리"
    ],
    "policy_alert": "하수처리장 안전 점검 관련 규제가 강화될 가능성이 있습니다.",
    "source": "Google News Korea 상하수도",
    "link": "https://news.google.com/rss/articles/CBMiaEFVX3lxTE5rdm1LNzJVaGdYRVdhRVNQN1F2V1RiR050c2FVcGFIekJIMGQ0VzNHNzV1QkhkT3BNLU1pUV9BbXlrWVI2QkJTRXctbUFCY0JJNG5tYWE4cnBOVUdlX0RPY3RpN1FTeE50?oc=5",
    "score": 26,
    "keywords": [
      "하수처리",
      "수처리",
      "하수처리장"
    ],
    "domestic": true,
    "region": "domestic",
    "source_type": "search_rss"
  },
  {
    "date": "2017-09-28",
    "title": "[글로벌 물산업 리더기업] 롯데케미칼, 수처리 분리막 사업 본격화 - 워터저널",
    "ko_title": "롯데케미칼, 수처리 분리막 사업 본격화",
    "brief": "롯데케미칼이 수처리 분리막 사업을 본격적으로 시작했습니다. 이로 인해 물산업에서의 경쟁력이 강화될 것으로 기대됩니다.",
    "summary": "롯데케미칼은 최근 수처리 분리막 사업을 본격화하며 글로벌 물산업에서의 입지를 강화하고 있습니다. 이 사업은 수처리 기술의 발전과 함께 환경 문제 해결에 기여할 것으로 보입니다. 분리막 기술은 물의 질을 개선하고 효율적인 수처리를 가능하게 하여 산업 전반에 긍정적인 영향을 미칠 것입니다. 롯데케미칼의 진출은 국내외 시장에서의 경쟁력을 높이는 중요한 계기가 될 것입니다.",
    "why_important": "롯데케미칼의 수처리 분리막 사업은 국내 수처리 시장의 기술 발전을 촉진할 것으로 예상됩니다. 이는 환경 규제 강화와 물 재이용 수요 증가에 대응하는 중요한 전략입니다.",
    "category": "분리막/MBR",
    "countries": [
      "한국"
    ],
    "companies": [
      "롯데케미칼"
    ],
    "technologies": [
      "분리막",
      "수처리"
    ],
    "policy_alert": "",
    "source": "Google News Korea 막여과 MBR",
    "link": "https://news.google.com/rss/articles/CBMickFVX3lxTFBhY29nalpjLVo5c21LaFVvNVRkTWNvTko0VDJsOExsQnRIcV9HR291dzRNcVg2dUdoTE84Q2t1TU5KSTRLWThLSXU3YXI2ZjJnLWgtTTVScm9HcFM4dkZWTXg4X0NjQjFxekQwN2JMZ2Z6Z9IBdkFVX3lxTE9RRzJpbzVTTW9YVEZXNy1aYnUwMU9ONDRRd3BpUlNxWkRRNkU4R0NpQXF4M0w2b013VHhIdTF2MzA4MVpYaUVPQ3RwTGpFVnhuVVJvbWNHeEs4SG5sYUxWa085eWRGcUNxQzFOcXhlbXp1WmMtRmc?oc=5",
    "score": 26,
    "keywords": [
      "수처리",
      "물산업",
      "분리막"
    ],
    "domestic": true,
    "region": "domestic",
    "source_type": "search_rss"
  },
  {
    "date": "2026-06-01",
    "title": "기장군수 선거 막판 흔드는 ‘일광 하수처리장 증설’… 정명시 “이전 추진” 정면돌파 - 녹색경제신문",
    "ko_title": "기장군수 선거와 일광 하수처리장 증설",
    "brief": "기장군수 선거를 앞두고 일광 하수처리장 증설이 주요 쟁점으로 떠올랐다. 정명시는 하수처리장 이전을 추진하겠다고 밝혔다.",
    "summary": "기장군수 선거가 다가오면서 일광 하수처리장 증설이 주요 이슈로 부각되고 있다. 정명시는 하수처리장 이전을 추진하겠다고 발표하며 선거 전략으로 활용하고 있다. 이와 관련하여 지역 주민들의 의견이 분분하며, 수처리 산업의 중요성이 강조되고 있다. 하수처리장 증설은 지역 환경 개선과 수자원 관리에 기여할 것으로 기대된다.",
    "why_important": "하수처리장 증설은 지역 환경과 수자원 관리에 중요한 영향을 미친다. 이는 수처리 산업의 발전과 관련된 정책 및 프로젝트에 영향을 줄 수 있다.",
    "category": "프로젝트/수주",
    "countries": [
      "한국"
    ],
    "companies": [],
    "technologies": [
      "하수처리"
    ],
    "policy_alert": "",
    "source": "Google News Korea 재이용수 PFAS",
    "link": "https://news.google.com/rss/articles/CBMiaEFVX3lxTE14bktqUUFSdzliaHE3My1jNnkxdHRXMl9GaGQ2b3pZdFZsdkcyako5UTl0bWFrdGdGbTUzcGxES3ZfWVI1UzZVd2pzOWdLazRadGRVeTQtQzA5YzRGR01OQkRGdVd4V0xp?oc=5",
    "score": 26,
    "keywords": [
      "하수처리",
      "수처리",
      "하수처리장"
    ],
    "domestic": true,
    "region": "domestic",
    "source_type": "search_rss"
  },
  {
    "date": "2026-03-30",
    "title": "美 공공 하수처리장에 韓 기술 첫 진출…'이 회사'가 해냈다 - 한국경제",
    "ko_title": "美 공공 하수처리장에 韓 기술 첫 진출",
    "brief": "한국 기업이 미국 공공 하수처리장에 기술을 처음으로 수출했습니다. 이는 한국 수처리 기술의 국제적 경쟁력을 보여주는 사례입니다.",
    "summary": "한국의 한 기업이 미국의 공공 하수처리장에 수처리 기술을 성공적으로 수출했습니다. 이로 인해 한국의 하수처리 기술이 해외 시장에 진출하는 중요한 이정표가 되었습니다. 해당 기술은 효율적인 하수 처리와 재이용수 생산에 기여할 것으로 기대됩니다. 이는 한국 수처리 산업의 글로벌 경쟁력을 강화하는 데 중요한 역할을 할 것입니다.",
    "why_important": "이 사건은 한국 수처리 기술의 국제적 확장을 의미하며, 향후 해외 프로젝트 수주에 긍정적인 영향을 미칠 것으로 예상됩니다. 이는 한국 기업들이 글로벌 시장에서 경쟁력을 갖추는 데 중요한 사례입니다.",
    "category": "프로젝트/수주",
    "countries": [
      "미국"
    ],
    "companies": [
      "한국 기업"
    ],
    "technologies": [
      "하수처리",
      "재이용수"
    ],
    "policy_alert": "",
    "source": "Google News Korea 재이용수 PFAS",
    "link": "https://news.google.com/rss/articles/CBMiWkFVX3lxTE83VS1KRWk1V0RfQ0dWUnhWZUd2SWRuOFA3VDJ3bkpESEtiZkJTTUNYUXBCNkVoa25fekRualhlSVZOWlVLTXRORW14clctU2VNTkxTUHh6Z2NNZ9IBVEFVX3lxTFB2M2Zxd3dlTlRJb0tpcFQySWZPUHB0dWZIdHNVX2FNSGo0OEhqdlBBbVcwWDVrZGJvbjBxR0JSNmEzWjc0U1BRNTNhSFk1V3l0UnBYYQ?oc=5",
    "score": 26,
    "keywords": [
      "하수처리",
      "수처리",
      "하수처리장"
    ],
    "domestic": true,
    "region": "domestic",
    "source_type": "search_rss"
  },
  {
    "date": "2024-11-25",
    "title": "Membrane Bioreactor Market Global Forecast to 2029 - Increasing Demand for Effective Wastewater Treatment, Rising Stringent Environmental Regulations Standards & Growing ...",
    "ko_title": "막생물반응기 시장 2029년까지 성장 전망",
    "brief": "막생물반응기(MBR) 시장이 2029년까지 성장할 것으로 예상됩니다. 환경 규제가 강화되면서 효과적인 하수처리에 대한 수요가 증가하고 있습니다.",
    "summary": "막생물반응기(MBR) 시장은 2029년까지 성장할 것으로 보이며, 이는 하수처리에 대한 효과적인 솔루션에 대한 수요 증가와 환경 규제의 강화에 기인합니다. MBR 기술은 다양한 막 유형과 시스템 구성으로 제공되며, 이는 하수 처리 효율성을 높이는 데 기여합니다. 이 시장의 성장은 수처리 산업에 긍정적인 영향을 미칠 것으로 예상됩니다. 특히, 환경 보호와 관련된 규제가 강화됨에 따라 MBR 기술의 필요성이 더욱 부각되고 있습니다.",
    "why_important": "MBR 기술의 성장은 수처리 시장의 혁신을 촉진할 수 있습니다. 또한, 환경 규제의 강화는 기업들이 지속 가능한 수처리 솔루션을 채택하도록 유도할 것입니다.",
    "category": "막생물반응기",
    "countries": [],
    "companies": [],
    "technologies": [
      "MBR",
      "막생물반응기"
    ],
    "policy_alert": "",
    "specs": [],
    "source": "Bing News Global MBR",
    "link": "http://www.bing.com/news/apiclick.aspx?ref=FexRss&aid=&tid=6a1e99b741d44230b22f7e366b091997&url=https%3a%2f%2ffinance.yahoo.com%2fnews%2fmembrane-bioreactor-market-global-forecast-114100669.html&c=16621848752719979235&mkt=en-us",
    "score": 51,
    "keywords": [
      "mbr",
      "membrane bioreactor",
      "membrane",
      "hollow fiber",
      "wastewater",
      "water treatment"
    ],
    "domestic": false,
    "region": "global",
    "source_type": "search_rss"
  },
  {
    "date": "2021-10-19",
    "title": "Watercore Membrane Bioreactor (MBR) : the highest effluent quality in wastewater treatment",
    "ko_title": "Watercore MBR: 하수처리에서 최고의 방류수 품질",
    "brief": "Watercore MBR은 환경적으로 민감한 지역에 방류할 수 있는 고품질의 방류수를 생산합니다. 이 기술은 재활용도 가능하여 수처리 산업에 중요한 역할을 합니다.",
    "summary": "Watercore의 막생물반응기(MBR)는 하수처리에서 높은 품질의 방류수를 생산하는 기술입니다. 이 시스템은 환경적으로 민감한 지역에 방류할 수 있으며, 재활용이 가능하여 수자원 관리에 기여합니다. MBR 기술은 기존의 하수처리 방식보다 효율적이며, 수처리 산업의 혁신을 이끌고 있습니다. 이러한 기술 발전은 지속 가능한 수자원 관리를 위한 중요한 요소로 작용합니다.",
    "why_important": "MBR 기술은 하수처리의 효율성을 높이고, 환경 보호에 기여하는 중요한 기술입니다. 이는 수처리 시장의 성장과 규제 준수 측면에서 중요한 의미를 가집니다.",
    "category": "분리막/MBR",
    "countries": [],
    "companies": [],
    "technologies": [
      "MBR",
      "막생물반응기"
    ],
    "policy_alert": "",
    "specs": [],
    "source": "Bing News Global MBR",
    "link": "http://www.bing.com/news/apiclick.aspx?ref=FexRss&aid=&tid=6a1e99b741d44230b22f7e366b091997&url=https%3a%2f%2fmenafn.com%2f1102994693%2fWatercore-Membrane-Bioreactor-MBR-the-highest-effluent-quality-in-wastewater-treatment&c=6585496301972639428&mkt=en-us",
    "score": 49,
    "keywords": [
      "mbr",
      "membrane bioreactor",
      "membrane",
      "wastewater",
      "effluent",
      "water treatment"
    ],
    "domestic": false,
    "region": "global",
    "source_type": "search_rss"
  },
  {
    "date": "2011-07-05",
    "title": "GE’s Next-Generation MBR Wastewater Treatment System Slashes Energy Use, Boosts Productivity",
    "ko_title": "GE, 차세대 MBR 수처리 시스템 출시",
    "brief": "GE가 차세대 막 생물 반응기(MBR) 수처리 기술인 LEAP*mbr을 발표했습니다. 이 기술은 에너지 사용을 줄이고 생산성을 높이는 데 기여합니다.",
    "summary": "GE는 싱가포르에서 LEAP*mbr이라는 차세대 막 생물 반응기(MBR) 수처리 기술을 소개했습니다. 이 기술은 수질 문제를 해결하고 에너지 효율성을 높이는 데 중점을 두고 개발되었습니다. MBR 기술은 하수 처리와 재이용수 분야에서 중요한 역할을 하며, 수처리 산업의 혁신을 이끌 것으로 기대됩니다. GE의 새로운 기술은 특히 에너지 소비를 줄이면서도 생산성을 향상시키는 데 기여할 것입니다.",
    "why_important": "이 기술은 수처리 산업의 에너지 효율성을 높이는 데 중요한 발전입니다. 또한, MBR 기술의 발전은 향후 수처리 시장의 경쟁력을 강화할 것으로 예상됩니다.",
    "category": "분리막/MBR",
    "countries": [
      "싱가포르"
    ],
    "companies": [
      "GE"
    ],
    "technologies": [
      "MBR",
      "막 생물 반응기"
    ],
    "policy_alert": "",
    "specs": [],
    "source": "Bing News Global MBR",
    "link": "http://www.bing.com/news/apiclick.aspx?ref=FexRss&aid=&tid=6a1e99b741d44230b22f7e366b091997&url=https%3a%2f%2fwww.businesswire.com%2fnews%2fhome%2f20110705005820%2fen%2fGE%25E2%2580%2599s-Next-Generation-MBR-Wastewater-Treatment-System-Slashes-Energy-Use-Boosts-Productivity&c=11449298112689961063&mkt=en-us",
    "score": 43,
    "keywords": [
      "mbr",
      "membrane bioreactor",
      "membrane",
      "wastewater",
      "water treatment"
    ],
    "domestic": false,
    "region": "global",
    "source_type": "search_rss"
  },
  {
    "date": "2026-02-18",
    "title": "MemCor™ MBR systems selected for three major wastewater treatment plant expansions in England",
    "ko_title": "영국 하수처리장 MBR 시스템 확장 선정",
    "brief": "영국의 세 개 주요 하수처리장에서 MemCor™ MBR 시스템이 선정되었습니다. 이는 수처리 산업의 확장과 기술 발전을 의미합니다.",
    "summary": "영국의 세 개 주요 하수처리장이 MemCor™ MBR 시스템을 도입하기로 결정했습니다. 이 프로젝트는 하수처리 용량을 확장하고, 효율성을 높이기 위한 투자로 해석됩니다. MBR 기술은 고도화된 수처리 솔루션으로, 환경 규제 준수와 수질 개선에 기여할 수 있습니다. 이러한 확장은 수처리 산업의 기술 발전과 시장 성장에 중요한 역할을 할 것입니다.",
    "why_important": "이 프로젝트는 하수처리 기술의 발전을 보여주며, 시장에서 MBR 시스템의 수요 증가를 나타냅니다. 또한, 환경 규제 강화에 대응하기 위한 기술적 해결책으로 중요합니다.",
    "category": "수처리 산업동향",
    "countries": [
      "영국"
    ],
    "companies": [],
    "technologies": [
      "MBR"
    ],
    "policy_alert": "",
    "specs": [],
    "source": "Bing News Global MBR",
    "link": "http://www.bing.com/news/apiclick.aspx?ref=FexRss&aid=&tid=6a1e99b741d44230b22f7e366b091997&url=https%3a%2f%2ffinance.yahoo.com%2fnews%2fmemcor-mbr-systems-selected-three-140000877.html&c=15153598790819934667&mkt=en-us",
    "score": 34,
    "keywords": [
      "mbr",
      "wastewater",
      "water treatment",
      "expansion",
      "investment"
    ],
    "domestic": false,
    "region": "global",
    "source_type": "search_rss"
  },
  {
    "date": "2025-12-05",
    "title": "Bee Ridge advanced wastewater treatment conversion becomes largest Membrane Bioreactor facility in the state - FOX 13 Tampa Bay",
    "ko_title": "비 리지 하수처리장, 주 최대 MBR 시설로 전환",
    "brief": "비 리지 하수처리장이 주에서 가장 큰 막 생물반응기 시설로 전환되었습니다. 이 시설은 고급 하수 처리 기술을 적용하여 운영됩니다.",
    "summary": "비 리지 하수처리장이 막 생물반응기(MBR) 시설로 전환되어 주에서 가장 큰 규모를 자랑하게 되었습니다. 이 시설은 고급 하수 처리 기술을 통해 수질 개선과 효율성을 높이고 있습니다. MBR 기술은 미세한 막을 사용하여 오염물질을 효과적으로 제거하며, 이는 수처리 산업의 혁신을 나타냅니다. 이러한 변화는 지역 사회의 환경 보호와 지속 가능한 수자원 관리에 기여할 것으로 기대됩니다.",
    "why_important": "이 시설의 전환은 수처리 기술의 발전을 보여주며, 지역의 수질 개선에 기여할 것입니다. 이는 향후 다른 지역에서도 유사한 기술 도입을 촉진할 수 있습니다.",
    "category": "분리막/MBR",
    "countries": [
      "미국"
    ],
    "companies": [],
    "technologies": [
      "막 생물반응기",
      "MBR"
    ],
    "policy_alert": "",
    "specs": [],
    "source": "Google News Global Membrane MBR",
    "link": "https://news.google.com/rss/articles/CBMizAFBVV95cUxPd1VzZjZrM3QyaE5SVTVqczJUSDRZdkI4elZSR1V5RGhsMVdQNXpNaEltQWFER2ZBWklia1RyZkhuckliZWViT3pnVWY2M1l1RzFOU2pIaThHbTdoWU0tbWxNMlJBSC1ZSnBVaGxTTkJwSGFBcmtDTHR6VHNybVBfQWpGV1dZLTRBSXp4U1kyeUJfT2I3dnpmVVFQMkFFLXBHZVE4dVV0YndhUkE2ck9OQXdQX2FPSTZ5ZzZmTzRnM3l4SWFiZDUzUG0xY2XSAdIBQVVfeXFMTndPZElDU0xTaXBma08yTV9mazludzc2N0lleXdWLVhrQnY4SzhqSFdpUENzZDNqQ09LS3ZGcHF1RHI4N1pnV2xwSk4wNFhUcDBWTDJ3ZTN1azNhS3daUHk4MG9kZGpKaFVab2tvVEZlRDFnYzhabGtJV2tNQ3FGZEI0M19hOVEwR3h4RUZNVWFOdWxTUmRjd3hzZnhzeDJIM2NXZFdITUxzdHFSZXh4RlZSN1oxV0ZKRHVGdjBoaEhFeVRlRmtpUlRERmg1QWE5MThR?oc=5",
    "score": 33,
    "keywords": [
      "membrane bioreactor",
      "membrane",
      "wastewater",
      "water treatment"
    ],
    "domestic": false,
    "region": "global",
    "source_type": "search_rss"
  },
  {
    "date": "2015-03-01",
    "title": "Water and Wastewater Treatment Technology Update",
    "ko_title": "수처리 기술 업데이트: 혁신적 접근법",
    "brief": "전력 발전소의 수처리 복잡성이 증가하고 있습니다. 혁신적인 처리 기술이 이를 해결하는 데 도움을 주고 있습니다.",
    "summary": "전력 발전소의 수처리 및 폐수 처리 과정이 점점 더 복잡해지고 있습니다. 최근에는 전방 삼투 및 막 생물 반응기와 같은 혁신적인 처리 기술이 발전하고 있습니다. 이러한 기술들은 수처리 산업에서의 효율성을 높이고, 환경 규제를 준수하는 데 기여할 수 있습니다. 특히, 막 기술의 발전은 다양한 산업에서의 수처리 문제 해결에 중요한 역할을 할 것으로 기대됩니다.",
    "why_important": "수처리 기술의 혁신은 시장의 경쟁력을 높이고, 환경 규제 준수에 필수적입니다. 이는 향후 수처리 산업의 성장과 지속 가능성에 중요한 영향을 미칠 것으로 추측입니다.",
    "category": "수처리 산업동향",
    "countries": [],
    "companies": [],
    "technologies": [
      "막 생물 반응기",
      "막",
      "폐수",
      "수처리"
    ],
    "policy_alert": "",
    "specs": [],
    "source": "Bing News Global MBR",
    "link": "http://www.bing.com/news/apiclick.aspx?ref=FexRss&aid=&tid=6a1e99b741d44230b22f7e366b091997&url=https%3a%2f%2fwww.powermag.com%2fwater-and-wastewater-treatment-technology-update%2f&c=4762957416080451425&mkt=en-us",
    "score": 33,
    "keywords": [
      "membrane bioreactor",
      "membrane",
      "wastewater",
      "water treatment"
    ],
    "domestic": false,
    "region": "global",
    "source_type": "search_rss"
  },
  {
    "date": "2026-05-26",
    "title": "\"버려지던 하수 방류수가 전기로\", 서산시, 공공하수처리장에 '친환경 소수력 발전' 도입 - v.daum.net",
    "ko_title": "서산시, 하수 방류수로 친환경 전기 생산",
    "brief": "서산시가 공공하수처리장에 친환경 소수력 발전을 도입합니다. 버려지던 하수 방류수를 활용하여 전기를 생산하는 혁신적인 프로젝트입니다.",
    "summary": "서산시는 공공하수처리장에 친환경 소수력 발전 시스템을 도입하기로 결정했습니다. 이 시스템은 하수 방류수를 활용하여 전기를 생산하는 방식으로, 환경 보호와 에너지 절약을 동시에 달성할 수 있습니다. 하수 방류수는 일반적으로 버려지지만, 이를 전력 생산에 활용함으로써 자원의 재활용이 가능해집니다. 이 프로젝트는 수처리 산업의 지속 가능성을 높이는 데 기여할 것으로 기대됩니다.",
    "why_important": "이 프로젝트는 하수 방류수의 재활용을 통해 에너지 자원을 확보할 수 있는 기회를 제공합니다. 이는 수처리 산업의 혁신적인 기술 발전을 나타내며, 향후 유사한 프로젝트의 확산 가능성을 시사합니다.",
    "category": "프로젝트/수주",
    "countries": [
      "대한민국"
    ],
    "companies": [],
    "technologies": [
      "소수력 발전",
      "하수처리"
    ],
    "policy_alert": "",
    "specs": [],
    "source": "Google News Korea 상하수도",
    "link": "https://news.google.com/rss/articles/CBMiRkFVX3lxTE10bXJsT1ZINHlKclZZaVdIMERyU3FGUm13OVItbXZ3UjRtTGxtYTdENmNtWHBSNHdUd1EtR1VBYlZfN29HQXc?oc=5",
    "score": 32,
    "keywords": [
      "하수처리",
      "수처리",
      "방류수",
      "하수처리장"
    ],
    "domestic": true,
    "region": "domestic",
    "source_type": "search_rss"
  },
  {
    "date": "2026-06-02",
    "title": "남해하수처리장 ‘전기설비 안전점검’ 실시 - 전남타임스",
    "ko_title": "남해하수처리장 전기설비 안전점검 실시",
    "brief": "남해하수처리장에서 전기설비 안전점검이 실시되었습니다. 이번 점검은 하수처리장의 안전성을 높이기 위한 조치입니다.",
    "summary": "남해하수처리장에서 전기설비에 대한 안전점검이 진행되었습니다. 이 점검은 하수처리장의 안전성을 확보하고, 운영 효율성을 높이기 위한 목적입니다. 하수처리 산업에서 전기설비의 안전성은 매우 중요한 요소로, 정기적인 점검이 필요합니다. 이번 점검을 통해 하수처리장의 전반적인 운영 안정성이 강화될 것으로 기대됩니다.",
    "why_important": "하수처리장의 전기설비 안전점검은 운영 효율성과 안전성을 높이는 데 중요합니다. 이는 수처리 산업의 신뢰성을 높이는 데 기여할 것입니다.",
    "category": "산업폐수",
    "countries": [
      "대한민국"
    ],
    "companies": [],
    "technologies": [],
    "policy_alert": "",
    "specs": [],
    "source": "Google News Korea 재이용수 PFAS",
    "link": "https://news.google.com/rss/articles/CBMiZkFVX3lxTFBsQV90TVZQUWF4cUFZTVdjdERUQXl2S1pJRERrdkJVQjYwSHd5eldoUzZnTmlESW5CR2hWUHNpeGhmV1NQRGFXbVNNR055Y2ZCQ3hnRzFCS1J4ektEZGJkRUtIRVpVQQ?oc=5",
    "score": 26,
    "keywords": [
      "하수처리",
      "수처리",
      "하수처리장"
    ],
    "domestic": true,
    "region": "domestic",
    "source_type": "search_rss"
  },
  {
    "date": "2026-05-28",
    "title": "전주시, 올해 하수처리장 운영·시설개선에 434억 투입 - 뉴시스",
    "ko_title": "전주시, 하수처리장 운영·시설개선에 434억 투입",
    "brief": "전주시는 올해 하수처리장 운영과 시설 개선에 434억 원을 투자한다고 발표했다. 이는 지역 수처리 인프라 개선을 위한 중요한 조치로 평가된다.",
    "summary": "전주시는 2023년 하수처리장 운영 및 시설 개선을 위해 434억 원을 투입할 계획이다. 이 투자는 지역 내 하수처리 시설의 효율성을 높이고, 환경 보호를 위한 기반을 마련하는 데 기여할 것으로 기대된다. 하수처리장 운영 개선은 수처리 산업의 지속 가능성을 높이는 중요한 요소로 작용할 수 있다. 이러한 투자는 지역 주민의 생활 환경 개선에도 긍정적인 영향을 미칠 것이다.",
    "why_important": "하수처리장 운영 개선은 지역 환경 관리 및 수질 개선에 필수적이다. 이는 수처리 산업의 발전과 관련된 중요한 프로젝트로, 향후 유사한 투자가 증가할 가능성이 있다.",
    "category": "프로젝트/수주",
    "countries": [
      "대한민국"
    ],
    "companies": [],
    "technologies": [
      "하수처리"
    ],
    "policy_alert": "",
    "specs": [
      "434000000"
    ],
    "source": "Google News Korea 상하수도",
    "link": "https://news.google.com/rss/articles/CBMiYEFVX3lxTE02VEpPb2lUQm5pOENiSzZ6QUdyWXdRYTJ4WS1kWHRPSVNyQlRkRlNGbFJvZzd3cmJpWjBZQkVrRDhlOG5rNGZwYk9sa1ZDTzJOaE5mdU9KQ01KSVI3WlUxQ9IBeEFVX3lxTE1VYVRXV3FZcXJQVXIzRmFDRG1ISGpzdVNDY096NFdtRnFKYmt5My1NVEJUbC1MY1JMRngtZU5TeW5nYm5Bb19HQ1U0UXVuenZXdkxveGFLWEQyVjM2WDJHLWN2OExjTlp3ZEUzTV9ERkVUWFRjcTB2OA?oc=5",
    "score": 26,
    "keywords": [
      "하수처리",
      "수처리",
      "하수처리장"
    ],
    "domestic": true,
    "region": "domestic",
    "source_type": "search_rss"
  },
  {
    "date": "2026-05-27",
    "title": "기획처, 울산 하수처리장 방문…에너지자립 전국 확산 지원 - 연합뉴스",
    "ko_title": "울산 하수처리장 방문, 에너지자립 지원",
    "brief": "기획처가 울산 하수처리장을 방문하여 에너지자립을 위한 지원 방안을 논의했습니다. 이는 전국적으로 에너지 자립을 확산하기 위한 노력의 일환입니다.",
    "summary": "기획재정부는 울산 하수처리장을 방문하여 에너지 자립을 위한 지원 방안을 모색했습니다. 이번 방문은 하수처리장 운영의 효율성을 높이고, 에너지 자립을 통해 지속 가능한 수처리 산업을 발전시키기 위한 것입니다. 정부는 하수처리장에서 발생하는 에너지를 활용하여 에너지 자립을 도모하고 있습니다. 이는 수처리 산업의 혁신과 지속 가능성을 높이는 데 기여할 것으로 기대됩니다.",
    "why_important": "이번 방문은 수처리 산업의 에너지 효율성을 높이고, 지속 가능한 발전을 촉진하는 중요한 계기가 될 것입니다. 이는 향후 관련 정책 및 기술 개발에 긍정적인 영향을 미칠 것으로 추측됩니다.",
    "category": "수처리 산업동향",
    "countries": [
      "대한민국"
    ],
    "companies": [],
    "technologies": [
      "하수처리"
    ],
    "policy_alert": "",
    "specs": [],
    "source": "Google News Korea 재이용수 PFAS",
    "link": "https://news.google.com/rss/articles/CBMiW0FVX3lxTE90dEI5MWFveGJSR3RuTjEwZHhPdi1iSnA4MTM0cDNIX1NDb0lyOFo1Z3hqZGFMX1hOODhQZC0wdmdMVm82bWprUmsxcGlmbWFseGhkWlhENUNEcDDSAWBBVV95cUxNWFhScWROZTROS09HaGdIckVUTGlCX2RUZVdDa0N4V2hHY3N2TjMtLURNdEdQcEg2cmtzWkVtUURaOTB3OUlla3dZN2VROEw3eXJNeXQyZmV2dGlwQS1pc0k?oc=5",
    "score": 26,
    "keywords": [
      "하수처리",
      "수처리",
      "하수처리장"
    ],
    "domestic": true,
    "region": "domestic",
    "source_type": "search_rss"
  },
  {
    "date": "2026-05-27",
    "title": "기획처, 하수처리장 에너지 자립화 확산 추진…내년 예산 반영 검토 - v.daum.net",
    "ko_title": "하수처리장 에너지 자립화 추진, 내년 예산 검토",
    "brief": "기획처가 하수처리장 에너지 자립화 확산을 추진하고 있습니다. 내년 예산에 반영할 계획을 검토 중입니다.",
    "summary": "기획재정부는 하수처리장의 에너지 자립화를 위한 정책을 추진하고 있으며, 이를 위해 내년 예산에 관련 항목을 반영할 계획입니다. 하수처리장에서 발생하는 에너지를 활용하여 운영비 절감과 환경 보호를 동시에 도모하고자 합니다. 이러한 정책은 수처리 산업의 지속 가능성을 높이는 데 기여할 것으로 기대됩니다. 에너지 자립화는 하수처리장 운영의 효율성을 높이는 중요한 요소로 작용할 것입니다.",
    "why_important": "하수처리장의 에너지 자립화는 운영 비용 절감과 환경적 지속 가능성을 동시에 달성할 수 있는 중요한 전략입니다. 이는 수처리 산업의 경쟁력을 높이고, 정부의 에너지 정책과도 연계될 가능성이 있습니다.",
    "category": "프로젝트/수주",
    "countries": [
      "대한민국"
    ],
    "companies": [],
    "technologies": [
      "하수처리",
      "에너지 자립화"
    ],
    "policy_alert": "하수처리장 에너지 자립화 관련 정책이 추진되고 있습니다.",
    "specs": [],
    "source": "Google News Korea 재이용수 PFAS",
    "link": "https://news.google.com/rss/articles/CBMiVEFVX3lxTE9OeTZXTmRFOWNpNUZEWG9rTHNhMU95aUZITl9GelFoMzZIb1NFOXhwazRyclVvTmJvTnR6MXJGRm8ySExhWHBxOTNoOEZ6ek9BM2h3eA?oc=5",
    "score": 26,
    "keywords": [
      "하수처리",
      "수처리",
      "하수처리장"
    ],
    "domestic": true,
    "region": "domestic",
    "source_type": "search_rss"
  },
  {
    "date": "2024-11-25",
    "title": "Membrane Bioreactor Market Global Forecast to 2029 - Increasing Demand for Effective Wastewater Treatment, Rising Stringent Environmental Regulations Standards & Growing ...",
    "ko_title": "막생물반응기 시장 전망 2029년까지",
    "brief": "막생물반응기(MBR) 시장이 2029년까지 성장할 것으로 예상됩니다. 환경 규제가 강화됨에 따라 효과적인 하수처리 수요가 증가하고 있습니다.",
    "summary": "막생물반응기(MBR) 시장은 2029년까지 지속적인 성장이 예상됩니다. 이는 하수처리에 대한 효과적인 솔루션에 대한 수요 증가와 함께 환경 규제가 강화되고 있기 때문입니다. MBR 기술은 다양한 막 유형과 시스템 구성으로 제공되며, 이는 하수처리 산업에서 중요한 역할을 하고 있습니다. 이러한 기술의 발전은 수처리 산업의 효율성을 높이고, 지속 가능한 물 관리에 기여할 것으로 보입니다.",
    "why_important": "MBR 기술의 발전은 하수처리 시장의 효율성을 높이고, 환경 규제 준수에 기여할 수 있습니다. 이는 수처리 산업의 경쟁력을 강화하는 중요한 요소입니다.",
    "category": "막생물/MBR",
    "countries": [],
    "companies": [],
    "technologies": [
      "MBR",
      "막생물반응기",
      "하수처리"
    ],
    "policy_alert": "",
    "specs": [],
    "source": "Bing News Global MBR",
    "link": "http://www.bing.com/news/apiclick.aspx?ref=FexRss&aid=&tid=6a1eccc49ebe402796df6b8def6c0883&url=https%3a%2f%2ffinance.yahoo.com%2fnews%2fmembrane-bioreactor-market-global-forecast-114100669.html&c=16621848752719979235&mkt=en-us",
    "score": 51,
    "keywords": [
      "mbr",
      "membrane bioreactor",
      "membrane",
      "hollow fiber",
      "wastewater",
      "water treatment"
    ],
    "domestic": false,
    "region": "global",
    "source_type": "search_rss"
  },
  {
    "date": "2021-10-19",
    "title": "Watercore Membrane Bioreactor (MBR) : the highest effluent quality in wastewater treatment",
    "ko_title": "Watercore MBR: 하수처리에서 최고의 방류수 품질",
    "brief": "Watercore MBR은 환경적으로 민감한 지역에 방류할 수 있는 고품질의 방류수를 생산합니다. 이 기술은 재활용에도 적합하여 수처리 산업에 중요한 역할을 합니다.",
    "summary": "Watercore의 막생물반응기(MBR)는 하수처리에서 매우 높은 품질의 방류수를 생산합니다. 이 방류수는 환경적으로 민감한 지역에 방류하거나 재활용할 수 있습니다. MBR 기술은 수처리 산업에서 효율성을 높이고, 환경 보호에 기여하는 중요한 기술로 자리잡고 있습니다. 이러한 고품질 방류수는 수자원 관리와 재이용에 있어 중요한 요소로 작용합니다.",
    "why_important": "MBR 기술은 수처리 산업에서 방류수 품질을 향상시키는 데 중요한 역할을 합니다. 이는 환경 규제 강화와 수자원 재이용 필요성 증가에 대응하기 위한 기술적 해결책으로 주목받고 있습니다.",
    "category": "분리막/MBR",
    "countries": [],
    "companies": [],
    "technologies": [
      "MBR",
      "막생물반응기"
    ],
    "policy_alert": "",
    "specs": [],
    "source": "Bing News Global MBR",
    "link": "http://www.bing.com/news/apiclick.aspx?ref=FexRss&aid=&tid=6a1eccc49ebe402796df6b8def6c0883&url=https%3a%2f%2fmenafn.com%2f1102994693%2fWatercore-Membrane-Bioreactor-MBR-the-highest-effluent-quality-in-wastewater-treatment&c=6585496301972639428&mkt=en-us",
    "score": 49,
    "keywords": [
      "mbr",
      "membrane bioreactor",
      "membrane",
      "wastewater",
      "effluent",
      "water treatment"
    ],
    "domestic": false,
    "region": "global",
    "source_type": "search_rss"
  },
  {
    "date": "2011-07-05",
    "title": "GE’s Next-Generation MBR Wastewater Treatment System Slashes Energy Use, Boosts Productivity",
    "ko_title": "GE, 차세대 MBR 수처리 시스템 출시",
    "brief": "GE가 LEAP*mbr이라는 차세대 막생물반응기(MBR) 수처리 기술을 선보였습니다. 이 기술은 에너지 사용을 줄이고 생산성을 높이는 데 기여합니다.",
    "summary": "GE는 싱가포르에서 LEAP*mbr이라는 차세대 막생물반응기(MBR) 수처리 기술을 발표했습니다. 이 기술은 수질 문제를 해결하고 에너지 효율성을 높이며 생산성을 향상시키는 데 중점을 두고 있습니다. MBR 기술은 특히 하수 처리 및 재이용수 분야에서 중요한 역할을 할 것으로 기대됩니다. GE의 새로운 시스템은 기존 기술보다 더 나은 성능을 제공하여 수처리 산업에 긍정적인 영향을 미칠 것입니다.",
    "why_important": "이 기술은 수처리 산업의 에너지 효율성을 높이는 데 기여할 수 있습니다. 또한, MBR 기술의 발전은 규제 및 환경 기준을 충족하는 데 중요한 역할을 할 것으로 추측입니다.",
    "category": "분리막/MBR",
    "countries": [
      "싱가포르"
    ],
    "companies": [
      "GE"
    ],
    "technologies": [
      "MBR",
      "막생물반응기"
    ],
    "policy_alert": "",
    "specs": [],
    "source": "Bing News Global MBR",
    "link": "http://www.bing.com/news/apiclick.aspx?ref=FexRss&aid=&tid=6a1eccc49ebe402796df6b8def6c0883&url=https%3a%2f%2fwww.businesswire.com%2fnews%2fhome%2f20110705005820%2fen%2fGE%25E2%2580%2599s-Next-Generation-MBR-Wastewater-Treatment-System-Slashes-Energy-Use-Boosts-Productivity&c=11449298112689961063&mkt=en-us",
    "score": 43,
    "keywords": [
      "mbr",
      "membrane bioreactor",
      "membrane",
      "wastewater",
      "water treatment"
    ],
    "domestic": false,
    "region": "global",
    "source_type": "search_rss"
  },
  {
    "date": "2026-02-18",
    "title": "MemCor™ MBR systems selected for three major wastewater treatment plant expansions in England",
    "ko_title": "영국 하수처리장 확장에 MemCor™ MBR 시스템 선정",
    "brief": "영국의 세 개 주요 하수처리장이 MemCor™ MBR 시스템을 도입합니다. 이는 수처리 산업의 기술 발전을 보여주는 사례입니다.",
    "summary": "영국의 세 개 주요 하수처리장이 MemCor™ MBR 시스템을 도입하기로 결정했습니다. 이 확장은 수처리 기술의 발전과 함께 하수 처리 효율성을 높이기 위한 노력의 일환으로 진행됩니다. MemCor™ MBR 시스템은 고효율 막 여과 기술을 사용하여 수질 개선에 기여할 것으로 기대됩니다. 이러한 프로젝트는 수처리 산업의 지속 가능한 발전을 위한 중요한 이정표로 작용할 것입니다.",
    "why_important": "이 프로젝트는 하수처리 기술의 혁신을 보여주며, 시장에서의 경쟁력을 강화할 수 있는 기회를 제공합니다. 또한, 환경 규제 강화에 대응하기 위한 기술적 진전을 나타냅니다.",
    "category": "분리막/MBR",
    "countries": [
      "영국"
    ],
    "companies": [],
    "technologies": [
      "MBR"
    ],
    "policy_alert": "",
    "specs": [],
    "source": "Bing News Global MBR",
    "link": "http://www.bing.com/news/apiclick.aspx?ref=FexRss&aid=&tid=6a1eccc49ebe402796df6b8def6c0883&url=https%3a%2f%2ffinance.yahoo.com%2fnews%2fmemcor-mbr-systems-selected-three-140000877.html&c=15153598790819934667&mkt=en-us",
    "score": 34,
    "keywords": [
      "mbr",
      "wastewater",
      "water treatment",
      "expansion",
      "investment"
    ],
    "domestic": false,
    "region": "global",
    "source_type": "search_rss"
  },
  {
    "date": "2015-03-01",
    "title": "Water and Wastewater Treatment Technology Update",
    "ko_title": "수처리 기술 업데이트: 혁신적 접근법",
    "brief": "전력 발전소의 수처리 및 폐수 처리가 복잡해지고 있습니다. 혁신적인 처리 기술이 이를 해결하는 데 도움을 줄 수 있습니다.",
    "summary": "전력 발전소에서의 수처리 및 폐수 처리는 점점 더 복잡해지고 있으며, 이에 대한 혁신적인 기술들이 등장하고 있습니다. 최근의 발전으로는 전방 삼투 및 막 생물 반응기(MBR)와 같은 기술이 포함됩니다. 이러한 기술들은 효율성을 높이고 운영 비용을 절감하는 데 기여할 수 있습니다. 수처리 산업에 있어 이러한 혁신은 지속 가능한 발전을 위한 중요한 요소로 작용할 것입니다.",
    "why_important": "수처리 기술의 혁신은 시장의 경쟁력을 높이고 운영 효율성을 개선하는 데 기여합니다. 이는 규제 준수와 환경 보호 측면에서도 중요한 의미를 갖습니다.",
    "category": "수처리 산업동향",
    "countries": [],
    "companies": [],
    "technologies": [
      "막 생물 반응기",
      "전방 삼투"
    ],
    "policy_alert": "",
    "specs": [],
    "source": "Bing News Global MBR",
    "link": "http://www.bing.com/news/apiclick.aspx?ref=FexRss&aid=&tid=6a1eccc49ebe402796df6b8def6c0883&url=https%3a%2f%2fwww.powermag.com%2fwater-and-wastewater-treatment-technology-update%2f&c=4762957416080451425&mkt=en-us",
    "score": 33,
    "keywords": [
      "membrane bioreactor",
      "membrane",
      "wastewater",
      "water treatment"
    ],
    "domestic": false,
    "region": "global",
    "source_type": "search_rss"
  }
]